[
  {
    "title": "Judge dismisses Kennedy Center suit against musician who canceled",
    "summary": "Lawyer for Chuck Redd, who pulled out after Trump renamed center, called case ‘political retribution’",
    "body": "Jazz drummer and vibes player Chuck Redd has successfully resisted a breach of contract lawsuit brought against him after he canceled a Christmas Eve performance at the Kennedy Center after the White House announced that Donald Trump’s name would be added to the facility. Redd’s lawyers confirmed that the suit had been dismissed by a judge, and the musician told the Associated Press he was “very pleased” by the ruling. Last week, another judge ordered the removal of Trump’s name from the facade and website of the center, ruling that the performing arts venue, designated as a living memorial to the late president by Congress, cannot be renamed without an act of Congress. Richard Grenell, then the Kennedy Center’s president, threatened to sue Redd soon after he pulled the plug on the gig, saying the center would seek $1m in damages for what he termed “this political stunt”. “Your decision to withdraw at the last moment – explicitly in response to the Center’s recent renaming, which honors President Trump’s extraordinary efforts to save this national treasure – is classic intolerance and very costly to a non-profit Arts institution,” Grenell informed the musician. The renamed center filed suit against Redd in March, accompanied by an offer to settle if Redd paid $7,500, played at this year’s concert, and refrained from issuing “political commentary” about his decision to withdraw from the center’s annual, free “Christmas Eve Jazz Jam”. On Friday, DC superior court judge Tanya Jones Bosier said Kennedy Center officials had failed to show they had made a legally binding agreement with Redd to perform and there was no contract in force to breach. “I could not find a valid breach-of-contract claim here,” Jones Bosier said before dismissing the lawsuit, according to the Washington Post. “There’s no dispute that he did not sign the 2025 agreement.” The judge granted Redd’s motion to dismiss under the District of Columbia’s anti-Slapp (Strategic Lawsuits Against Public Participation) law, designed to stop legal action being taken just to silence opposing points of view on matters of public interest. “The Center sued Mr Redd because he publicly and rightly objected to adding Donald Trump’s name to the Kennedy Center, a living memorial to former President John F Kennedy,” Lisa J Banks, one of Redd’s lawyers, said in a statement. “The lawsuit against Mr Redd was political retribution, pure and simple, by the Trump Kennedy Center, and the Court correctly saw it as such in dismissing the case with prejudice.”",
    "body_chars": 2539,
    "body_truncated": false,
    "url": "https://www.theguardian.com/us-news/2026/jun/06/judge-dismisses-kennedy-center-musician",
    "section": "US news",
    "published": "2026-06-06T21:01:06Z",
    "source": "Guardian"
  },
  {
    "title": "Palestinian baby shot dead by Israeli troops in occupied West Bank",
    "summary": "The seven-month-old, Sam Fahd Abu Haikal, was in his mother’s arms when soldiers fired on family in Hebron",
    "body": "Israeli troops killed a seven-month-old Palestinian baby in the occupied West Bank and injured his parents after opening fire on the family’s car, despite it having complied with an order to stop. Soldiers opened fire on Friday on a car carrying the infant and his parents in the Tel Rumeida area of Hebron. The seven-month-old, Sam Fahd Abu Haikal, was critically injured, evacuated in critical condition to a hospital, where he later died. The boy turned seven months on Friday, the day he was killed. The Israeli military said troops had fired at a vehicle they believed was moving towards them, but an initial inquiry found those injured were uninvolved civilians. In an interview with Israeli newspaper Haaretz, the father, Fahd Abu Haikal, a lecturer at Bethlehem University, said that “a bullet passed through his hand and struck his son, Sam, who was being held by his mother in the back seat”. Abu Haikal said the family, which also included the couple’s 11-year-old son and Abu Haikal’s mother, had been driving through Hebron on Friday evening when soldiers signalled for the vehicle to stop, he said. He said it was still daylight and that the soldier who opened fire could clearly see the occupants were a family. “The soldier signalled me to stop. I brought the car to a complete halt and raised my hands on the steering wheel. Immediately afterwards, they opened fire on the vehicle,” he told Haaretz. The Israel Defense Forces said its troops “perceived a vehicle accelerating toward them” and one of the soldiers “responded with single shots toward the vehicle”. “As a result, three Palestinians were injured and evacuated for medical treatment,” the IDF said, adding that “the incident is under review” and expressed “deep sorrow for any harm caused to uninvolved individuals”. Abu Haikal rejected the military’s account. “The soldier was about 10 metres away from me. He saw me, he saw my wife and the children,” he told Haaretz. “The windows were not tinted, it was broad daylight and everything was clear. You can’t say he didn’t see that it was a family. “I stopped as I was instructed to, and then they simply shot at the car,” he added. “There was no clear checkpoint, just soldiers standing in the street. I stopped when I was asked to, and then the shooting started,” he said. Speaking at the boy’s funeral on Saturday, the father said “the soldier opened fire, then pulled back his unit and just walked away without a single word or a second thought”. “The car was completely stationary when he shot at us, it wasn’t moving at all. A seven-month-old infant killed in cold blood. He didn’t deserve this,” he added. Abu Haikal called for an investigation and said the soldier responsible should be held to account. “I demand and expect, if there is any conscience, any law, any morality, that the soldier who fired the shots will be held accountable for his actions. This case must not be closed without an investigation and without accountability. At the very least, I do not intend to give up.” Abu Haikal told the Associated Press that his wife was in critical condition, with shrapnel close to her heart. The family told her that her son was killed just before heading to funeral prayers. The baby’s body was wrapped in a Palestinian flag. His father carried him. The men placed the small bundle at their feet and bowed in prayer. The British consulate in Jerusalem said on X that it was “shocked and saddened” by the killing of the baby, calling for an “immediate and transparent investigation and accountability”. In a similar incident, Israeli troops operating in Tamoun, in the northern Jordan valley, opened fire on a vehicle travelling through the village on 15 March, killing a Palestinian couple and two of their children. The victims were identified as Ali Bani Odeh, 38, his wife, Waad Bani Odeh, 36, and their sons Othman, six, and Mohammad, five. According to the Israeli human rights group B’Tselem, soldiers removed two other children from the vehicle, Khaled, 11, and Mustafa, eight, both of whom suffered minor shrapnel injuries. The organisation said the troops then subjected Khaled to a violent interrogation at the scene. B’Tselem said the military initially prevented ambulances from reaching the area and allowed medical teams access only after a delay. The organisation added that soldiers later confiscated the family’s vehicle, which it said was riddled with bullet holes. The UN said last month that more than 1,000 Palestinians had been killed in the West Bank and East Jerusalem since the war began, at least 240 of them children, and 49 people have been killed this year. Israeli soldiers accused of harming Palestinians are rarely penalised and were indicted in less than 1% of cases based on 2,427 complaints alleging wrongdoing between 2016 and 2024, according to Israeli rights group Yesh Din. In the Gaza Strip, Israeli strikes killed nine people on Saturday, medical sources and the territory’s civil defence said. Israel’s military said one of the dead was a Hamas “terrorist cell commander”. In Gaza City, a drone strike killed seven people and wounded 15 others in the Jawazat camp for displaced people, according to the civil defence, a rescue service that operates under the authority of Hamas. The city’s al-Shifa hospital also reported receiving six bodies. “We targeted terrorists in that sector,” the Israeli army told AFP, without providing further details. The civil defence announced in the evening a eighth person had been killed in an Israeli strike in south-east Gaza City, identifying him as a 37-year-old man. Farther south, Muhannad Othman Farwana, 25, was killed in the morning in a strike on a tent, the civil defence said. Nasser hospital in Khan Younis said the man’s body was brought in along with several wounded. In a statement, the Israeli army said Farwana was “a terrorist cell commander in the military wing” of Hamas, adding he was killed in a precision strike. The strike had hit his tent on the roof of his house. He was due to get married later in the day, his cousin Mohammed Farwana said. “The whole family was ready to celebrate his wedding. Now, we’re attending his funeral instead of his marriage,” he told AFP. Additional reporting by Agence France-Presse",
    "body_chars": 6258,
    "body_truncated": false,
    "url": "https://www.theguardian.com/world/2026/jun/06/palestinian-baby-shot-dead-israeli-troops-occupied-west-bank",
    "section": "World news",
    "published": "2026-06-06T20:15:18Z",
    "source": "Guardian"
  },
  {
    "title": "Suit filed against controversial planned Stratos datacenter project in Utah",
    "summary": "Plan backed by Shark Tank’s Kevin O’Leary had footprint reduced but concerns remain over its health impacts",
    "body": "Utah residents have teamed up with a progressive non-profit organization to sue over an under-development AI datacenter backed by celebrity investor Kevin O’Leary, claiming the planned Stratos project facility “irrevocably” cuts off citizens’ rights by not allowing sufficient public input. Filed by the Alliance for a Better Utah and five unnamed residents of the Box Elder county area where the center is being developed, the lawsuit comes as Shark Tank co-host O’Leary agreed to scale back the physical footprint for the project. The alliance and residents are contesting the constitutionality of the state’s military installation development authority (Mida) – a special entity that oversees the datacenter’s proposal – and its approval of the project, NBC News reported. “Under the Stratos plan, it would hold permanent, irrevocable control over public health, safety, taxation and land use across tens of thousands of acres of Box Elder county, with no voter recourse,” plaintiffs’ attorney David Irvine said in a statement. Officials for the state and Mida said they are reviewing the lawsuit. Initial proposals for the datacenter envisioned a 40,000-acre (16,200-hectare) campus in Utah’s Hansel valley, but O’Leary on Wednesday told NBC that he is “going to have to” slim down the project. The Utah state senate president, Stuart Adams, later said O’Leary had agreed to a reduction in size, a commitment of water to the Great Salt Lake and “thousands of acres to be set aside for open space, wildlife protections and continued agricultural use”. Adams added that the Stratos project is in its “earliest stages” and a full permitting and environmental review process will be carried out. O’Leary posted on X that he is “not walking away from the Utah project, but I also understand why [state senate] president Adams sent the letter demanding major changes”. “A 75% reduction simply isn’t realistic for a project of this scale, but that doesn’t mean the concerns should be ignored,” the post added. O’Leary nonetheless accused opponents of the project of mounting “coordinated misinformation campaigns” and said public debate “has been fueled by outdated information”. He added that “claims that we’ll drain the Great Salt Lake, consume Utah’s power, or create massive environmental damage simply don’t reflect the reality of what we’re building”. He also pointed to the creation of construction jobs and other high-paying tech jobs, and billions of dollars of investment. O’Leary said he was also investigating the funding of AI datacenter opposition groups and had turned over evidence to federal authorities that he said appear to show links between the groups and “Chinese backed interests”. The accusation comes as four congressional Republicans, including Kentucky’s Brett Guthrie, chair of the House committee on energy and commerce, called on the FBI for information about “foreign influence campaigns working to slow American AI progress”. Guthrie said in a statement: “Datacenters are the foundational computing structure that makes modern life possible.”",
    "body_chars": 3073,
    "body_truncated": false,
    "url": "https://www.theguardian.com/us-news/2026/jun/06/stratos-datacenter-utah-suit",
    "section": "US news",
    "published": "2026-06-06T20:07:35Z",
    "source": "Guardian"
  },
  {
    "title": "Personal loans booming as cost of living drives Australians to borrow record amounts",
    "summary": "National debt helpline calls have increased alongside growth in new personal loans, which charged an average 9% interest in March",
    "body": "Australians are borrowing record amounts in personal loans as a long-term buildup in living costs wipes out savings buffers. New personal loans issued by banks reached a record $5.1bn in the first three months of 2026, according to Australian Bureau of Statistics data. While personal loans can be used to fund big-ticket items such as weddings, overseas trips or home renovations, they are also used to pay off regular bills or other debts. Andrew Grant, a professor of finance at the University of Sydney, said an increase in personal loans was typically a sign of intense financial pressure, often taken out by people who are struggling to make it paycheck to paycheck. Issuance of personal loans had fallen to less than $2bn per quarter from 2017 to 2021, when inflation and housing costs were lower, but rose sharply when interest rates began rising. New personal loans charged an average 9% interest in March, while new mortgage rates averaged 5.9%, according to the Reserve Bank. “Interest rates have risen [and] rents … and mortgages have gone up, so getting through the week has gotten a lot more challenging for people,” Grant said. “People are under a bit more financial stress and they feel like they may need a bit of assistance.” Personal refinancing loans have also steadily risen, which Grant said could indicate Australians have been increasingly forced to consolidate or pay off other personal debts. “As inflation is starting to grow, there’s not as much spare money for people to work around,” he said. Sign up for the Breaking News Australia email Car loans have not grown at the same rate, holding steady at over $4.7bn in new loans issued each quarter since 2024, the data shows. Separate RBA data released on Wednesday showed personal lending has grown 4.3% in the year to April, continuing a resurgence that started in 2023. Banks had been steadily cutting their total stock of personal and other non-mortgage loans since 2015, prudential regulator data shows. The RBA in 2019 attributed this to banks’ lower “risk appetite” and stronger responsible lending obligations. It also pointed to mortgage-holders’ ability to access offset and drawdown accounts to fund personal spending. Kevin James, chief solutions officer at credit monitoring agency Equifax, says the market for personal loans had also been “chewed up” by buy-now, pay-later companies until they faced stronger regulation in 2025. “It became more regulated and had more friction, then I think people changed and were quite happy to do a personal loan,” James said. Equifax has recorded steady growth in applications for personal loans over the past two years, but falling applications for buy-now, pay-later credit and car loans. ANZ said demand for “unsecured credit” through personal loans had been gradually increasing due to customers’ demands and the broader economy. Westpac’s chief executive, Anthony Miller, said personal loan inquiries had increased again in April after the Reserve Bank raised interest rates twice in the preceding two months. The RBA hiked rates again in May. Commonwealth Bank began rebuilding its consumer loan book in 2022 and now has more than $16bn on issue. ANZ followed in 2023, while Westpac and Macquarie turned around last year. Latitude, a major non-bank lender, estimates major banks are responsible for the “vast majority” of personal lending. Latitude still reported record loan applications and granted $3.3bn in loans for the year to June 2025, reporting that its non-vehicle loans over 2025 were spent on home improvement (38%), debt consolidation (24%), travel (15%) and other miscellaneous personal spending. Pawnshop Cash Converters, which previously focused on payday loans, has also moved into larger personal loans. Kristy Robson, a managing financial counsellor at the Consumer Action Law Centre, said the growth in lending had been accelerated by automatic online loan approvals. “The frictionless approval processes are damaging people’s financial capacity,” Robson said. “It’s become so automated that individual customers’ circumstances aren’t being considered appropriately, and they’re getting same-day approval on massive personal loans that they’re reaching for because they’re in financial hardship.” The national debt helpline has seen an increase in people calling in with issues due to personal loans, Robson said. “People really are struggling to make it through,” she said. “How, with the responsible lending laws, are they possibly getting approved?”",
    "body_chars": 4506,
    "body_truncated": false,
    "url": "https://www.theguardian.com/business/2026/jun/07/personal-loans-record-highs-australia-debt-borrowing-cost-of-living",
    "section": "Business",
    "published": "2026-06-06T20:00:13Z",
    "source": "Guardian"
  },
  {
    "title": "‘How do we know you won’t be the next John Fetterman?’: bruised Democrats weigh how to win back voters",
    "summary": "The party may reclaim the US House and even Senate, but primary candidates are far from united on how to move forward",
    "body": "Across the country, in front yards and on main streets, at dairy breakfasts and inside breweries, voters are delivering a similar message to Democratic primary candidates: they’re tired of both parties, and sick of being ignored. The Democratic party brand is bruised after its disastrous 2024 presidential loss. A botched review of the defeat by the Democratic National Committee, and a drawn-out process over releasing the so-called autopsy, created another round of handwringing over the party’s direction. On doorsteps, though, the voters don’t bring up the autopsy, or the party’s brand, according to candidates nationwide. They want a party that will stand up to Trump, fight for their healthcare and housing, make life more affordable, rein in immigration agents, build up their schools, get the US out of war and lower gas prices, protect their jobs from AI, confront the climate crisis and prevent datacenters from coming in. And many remain skeptical the Democrats can do all – or even part – of that. “It’s less about the bickering amongst Democrats and more about folks feeling like there are fewer people who give a shit in politics,” said Francesca Hong, a Democratic candidate for governor in Wisconsin. The Guardian spoke to candidates, lawmakers and operatives about where the party now stands, 19 months after Donald Trump’s victory over Kamala Harris – and five months before the next set of crucial US elections. The midterm headwinds show Democrats in a strong place to win back the US House of Representatives, and possibly the Senate, in November. But the contours of that wave are yet to be determined, and Democratic primary candidates are far from united on how the party should align itself and move forward. Some are charting a moderate path, while others have embraced leftwing populism. While few candidates are fixated on perceptions about the Democratic party’s brand, these perceptions nonetheless affect their races, and whether voters believe they can deliver. Ken Martin, the chair of the DNC, acknowledged after releasing the autopsy that the Democratic brand “is in trouble”, noting that ballot measures based on Democratic policies often win in places where candidates do not. “We have to restore confidence in our party and show we can really deliver on our campaign promises to the American people,” he wrote. Beyond the midterms, the Democrats believe they need to compete everywhere, rebuilding in areas they’d previously written off in rural, red-leaning parts of the country. The goal is not always to win, but to lose by less. Mallory McMorrow, a state legislator and Democratic candidate for US Senate in Michigan, recently held a roundtable in a swing county with Trump voters to try to understand why they voted for him, and what they think of him now. One man said he voted for Trump because he promised to blow up the system, bring jobs back to the US and end wars, McMorrow said. Trump has fallen short of many such promises. But the man McMorrow met didn’t believe anybody in Washington understands how much people like him are struggling. Democrats can’t assume that voters angry at Trump will simply turn out and vote for them instead, McMorrow said. “I just don’t want Democrats to take for granted that Republicans are giving us every opportunity, but we got to be aggressive, we got to fight, and we got to fight for people and make some people uncomfortable.” Primaries serve as a way for the party to publicly hash out its next steps. Chris Rabb, a state lawmaker from Philadelphia who won his primary in the bluest district in the US and faces no general election challenger, said he believes establishment politics is on the ballot right now, too. Voters need to feel like the party is committed to the “people closest to the pain”, rather than the donor class, he said. “Most incumbents are never seriously challenged, so that’s how you build that entrenchment, that complacency, sometimes hubris,” Rabb said. “If you never have to worry about losing, who’s holding you to account?” Out of touch? Martin won his bid to become DNC chair in February 2025, after promising to conduct – and release – a review of the presidential election loss. But the months wore on, and no report was published. Martin described the report as not “ready for primetime” and controversially decided not to release it. A host of other groups, from centrists to progressives, wrote their own versions of what went wrong in 2024. Martin didn’t want to “create a distraction”, he wrote in a blog post when the report was finally published last month. “Ironically, in doing so, I ended up creating an even bigger distraction.” The report is lacking in detail and data, and what it did not include stands out more than what it did. Joe Biden’s age – perhaps the central deficit of his re-election campaign, which he dropped in July 2024, making way for Harris – is not addressed. There is no mention, either, of the war in Gaza, a key schism on the left during the election. The effect was a sense that the party has yet to seriously grapple with its deficiencies, making it hard for some voters to see the Democrats as their long-term political home. Abbas Alawieh, a leader in the uncommitted movement, which advocated for Democrats to support a ceasefire in Gaza, is now running for state senate in Michigan and said war remains a central electoral issue for voters of all backgrounds, who want Democrats to be the anti-war party. “The fact that the autopsy report did not grapple with that issue, I think it’s just a further indication that the party’s out of touch with where voters are,” said Alawieh. Abdul El-Sayed, a former public health official running for US senate in Michigan, said voters may not bring up the autopsy, but they have a “broader frustration” with the party and a lack of leadership – and how this affects issues from healthcare costs to US spending on bombs abroad. “These are the issues that keep people up at night, and they feel like the party is just completely absent from the playing field, trying to fight the last battle, and even then, fought it poorly,” El-Sayed said. “So, I think people want a Democratic party that is willing to show up and fight on the issues that are the most important in their lives, and they’re just not seeing that.” The battles over the autopsy, which largely played out in the media or on leftwing podcasts or among the donor class, have not affected the day-to-day lives of voters the party hopes to reach. “They don’t even know what ‘DNC’ stands for,” Rabb said. But Julius Hernandez, a Democratic consultant in Colorado, also said the “petty little fights” over an election nearly two years ago are a distraction. “Voters are looking at us like: ‘Hey, how are you going to stop Donald Trump?’” he said. Searching for sanity Democrats in red and rural states have been arguing for many years that the party must invest more time and money in their areas so they can communicate with voters who used to be part of their coalition. Instead, it has largely concentrated on seven to 10 battleground states, and messages from the party nationally have tended to represent coastal areas, said Jane Kleeb, chair of the Nebraska Democratic party. Curtis Hertel Jr, chair of the Michigan Democratic party, said two county parties in his state that were defunct for more than a decade are now back online. He visited 32 counties last year, and his party has held town halls in red areas. Hertel walked in the parade at the Mesick mushroom festival, in a deep red part of the state. “They told me I was going to get yelled at and spit on,” he said. “People were actually excited that a Democrat was actually showing up to have a conversation.” Recalling a line from the movie The American President – “If you don’t give people water, they’ll drink sand” – Hertel said Trump “is bullshit and blame”, and wins elections through division. In other words, he’s got people drinking sand. “We’ve got to give people water,” said Hertel. “If we’re not the party fighting for higher wages or lowering the cost of healthcare, if we’re not the party of making childcare more affordable or making it easier for a family to own a home, there won’t be a party in America that’s fighting for those things.” How Democrats set about pouring that water depends on their priorities, and their districts. In Arizona, where statewide candidates who win tend to be more moderate Democrats, campaigns are tailored toward winning over independents and moderate Republicans, said Stacy Pearson, a Democratic consultant in the south-western state. It’s not fair to look at the Democratic brand in isolation, because the Republican party “has gone absolutely batshit”, she said. Democrats have struggled to define what they are for – instead just saying they are “against that tinfoil hat brigade” – but they are getting better, she said. “Folks are frustrated with this system, and the parties are the system,” Pearson said. “What we find is that, particularly Democrats in Arizona, who are a minority, just want sanity. They are against the extremes on both sides, and they just want government to function. They want to call when the streetlight’s out and have someone pick up the phone.” Avoiding heartbreak In a swing district in western Wisconsin, Rebecca Cooke is running again to unseat Republican representative Derrick Van Orden. If she says she’s a Democrat, a lot of times voters dismiss her outright. But if she starts with her background and her values, they’re more open to talk. “They want people in Congress that really give a shit about their livelihood, their farm, their public school, their hospital, and that’s whether they’re a Democrat or a Republican,” Cooke said. They’re sick of “limousine liberals and caviar conservatives”, she said. They want a clear roadmap of what will happen if Democrats win back the House and, eventually, control in Washington. “There is no perfectly worded statement or agenda t…",
    "body_chars": 12868,
    "body_truncated": true,
    "url": "https://www.theguardian.com/us-news/2026/jun/06/democrats-win-back-voters",
    "section": "US news",
    "published": "2026-06-06T18:07:06Z",
    "source": "Guardian"
  },
  {
    "title": "Despite new allegations, Maine’s Platner predicts voters will send him to Senate",
    "summary": "Democrat denies reports of physical intimidation towards women, saying his past has been ‘weaponized’",
    "body": "The Democratic US Senate candidate Graham Platner on Friday predicted that Maine’s voters would support him four days later in his party primary despite a string of controversies – including recent negative headlines about his treatment of women that he said had been “weaponized”. In a 25-minute speech before supporters in Bar Harbor, the oyster farmer and US marine combat veteran addressed the controversies about his personal conduct, which escalated on Thursday with a New York Times report in which three former romantic partners described disturbing behavior, including being physically intimidated by him. “When hurtful things I said on the internet a decade ago came out into the public, as I shared my personal journey through PTSD and darkness, of recovery and accountability and growth, Maine had my back,” Platner said at the rally. “Now, as every single piece of that past and journey gets dug up, litigated and weaponized, you have my back.” The first-time candidate, who is seeking to oust the Republican US senator Susan Collins in November, said: “When politically motivated, serious and false accusations are made against me, Maine, you have my back. The state of Maine raised me. And the state of Maine saved me.” Maine’s primary vote on Tuesday looms as Democrats try to retake a majority in Congress for the latter half of Donald Trump’s second presidency. In the run-up to the contest, Platner initially faced revelations that he had a tattoo recognized as a Nazi SS symbol. He has since had the tattoo removed and said he didn’t realize its meaning. Platner more recently has contended with media coverage of sexually explicit messages he sent to women while he was married – as well as the mixed report card of his behavior toward women in the Times. One woman said Platner twisted her arm during an argument and locked her in a room – an allegation he has denied. Platner has retained support from senior Democrats and independent politicians who caucus with the Democratic party. That includes the US senators Bernie Sanders of Vermont, Elizabeth Warren of Massachusetts and Ruben Gallego of Arizona. At his campaign stop on Friday, Platner was joined by US House member Ro Khanna, a progressive California Democrat. “We reject, unequivocally, misogyny,” Khanna said. “But you know who else rejects it? Graham Platner. “He understood that those years … were not the best years of his life.” Democratic voters at the rally said they were prepared to overlook Platner’s shortcomings. Galen Lowe told the Portland Press Herald it was“refreshing to have someone actually own up to stuff that they’ve done and say, yeah, that wasn’t such a great idea. I’m working to be a better person.” Former Platner campaign staffer Genevieve McDonald told the Associated Press that the candidate was “sexting multiple women while married” – and that “the campaign tried to assess that as an election vulnerability”. Two feminist political groups, the National Organization for Women Pac and Vote for Equality, have encouraged Maine voters to vote for the state’s governor, Janet Mills. Mills stepped down from Maine’s US Senate race but is still on the ballot. Some of the governor’s supporters are encouraging her to reactivate her campaign. A source close to Mills inconclusively told NBC News on Friday that “the governor remains on the ballot, and in the wake of this week’s stories, people across Maine are reaching out to tell her they’re voting for her and encouraging her to get fully back into the race”.",
    "body_chars": 3524,
    "body_truncated": false,
    "url": "https://www.theguardian.com/us-news/2026/jun/06/graham-platner-main-senate-physical-intimidation-allegations",
    "section": "US news",
    "published": "2026-06-06T17:58:54Z",
    "source": "Guardian"
  },
  {
    "title": "‘It’s like they’re kidnapped there’: families tell of distress over ‘inhumane’ ICE jail",
    "summary": "As detainees go on hunger strike over conditions at Delaney Hall, relatives describe concern for loved ones’ wellbeing",
    "body": "In mid-May, Elder Guerra was showering inside the Delaney Hall immigration detention facility when he slipped and fell. Guerra, a Guatemalan immigrant, has been locked up in the New Jersey jail for nearly five months. He was arrested by federal Immigration and Customs Enforcement (ICE) officials in Newark in January while helping a friend move his snowed-in car. Officers had approached and asked a few questions, according to a relative who spoke with the Guardian. Guerra has been in the US for eight years and is now fighting his deportation case while inside the detention center, where some of those detained have been on a hunger and labor strike to protest conditions, and which has been the scene of fierce protests for the last two weeks. Guerra’s fall was a bad one. He slammed the back of his skull against the floor and was knocked unconscious, and began having a seizure, according to the relative who received accounts from other detainees. Others detained in the unit were reportedly alarmed and pleaded with guards to call an ambulance. After much begging by other detainees, Guerra was taken to a hospital. He was transferred back into Delaney Hall that same week and placed in a medical isolation cell. “It’s been almost three weeks and he’s getting worse,” Guerra’s relative told the Guardian, requesting anonymity for fear of retaliation by ICE. “His head hurts. When he looks at the light, it bothers him, he gets fatigued. When he looks at a television screen, he feels dizzy. When he stands up and wants to walk, he gets dizzy.” “He needs medical attention. He’s not in an adequate place to recover,” the relative said, adding that Guerra is beginning to lose his hearing in his left ear. Guerra is one of two men held inside medical isolation cells inside Delaney, according to New Jersey congressional representative LaMonica McIver. A third man detained in that unit, who uses a wheelchair, was released on Thursday afternoon. The Delaney Hall facility, run by the private prison company GEO Group, opened last year and has faced repeated accusations of substandard medical care, inedible food and neglectful guards. Multiple oversight visits by members of congress have found conditions at the facility to match claims by detainees, according to the lawmakers’ accounts. Amid the hunger and labor strike inside and demonstrations outside, government officials – first ICE officers and then New Jersey state police and Newark police – have responded by pepper spraying, tasing, beating, deploying tear gas and arresting dozens of protesters. Families of immigrants detained inside Delaney Hall have had to navigate on-again, off-again visitation permission and chaos to visit their loves ones. Some told the Guardian how upset, angry and worried they are about their relatives, hoping they will be released soon to continue their immigration cases. Guerra’s relative has visited him since his fall and spoke about it through tears. “He kept telling me, ‘Help me. I need to leave here,’” the relative said. “But I told him, ‘I can’t do anything, because it’s not in my hands.’ I’m trying to pay for an attorney for them to do something.” He recalled touching his loved one’s neck and feeling the heat from a fever he was experiencing. Now, back on the outside, Guerra’s relative is having trouble focusing on anything other than fretting about his detained family member. “After the accident, what makes me saddest is what’s happening to the Hispanic community in this country,” he added. “They’re treating us like animals, like we’re not worth anything. We’re not criminals, we’re workers, we’re struggling to get out ahead.” Last Tuesday, under blazing early June sunshine and surrounded by state police barricades, protesters and reporters, Christopher Castro and his mother arrived at Delaney Hall for their first visit in weeks. They had driven nearly three hours from their home town on Long Island to the east of New York City for a 30-minute visit with Christopher’s father. “My dad told me that a lot of people inside are pushing their lawyers to get them out,” Castro said after the visit. Their loved one inside was not participating in the strike for fear of retaliation. “It’s been crazy. I hope they all get released and we can work on this [immigration case] on the outside.” Relatives came and went during the afternoon. One mother and daughter cried as they walked to their car after visiting a relative. Another woman and a young boy with neatly slicked hair and a polo shirt watched while they waited their own turn to enter the large, grim-looking, barbed-wired facility, the boy holding the woman’s hand in silence. On Tuesday night, detained immigrants inside Delaney Hall released a fourth public letter since the strike began, dated 31 May, repeating their claims about conditions inside. “The conditions in this prison are not fit for human beings over such a long period of time: medical neglect, water unfit for consumption, food that is past its expiration date and in poor condition, bathrooms that are unusable, and ventilation systems that have never been maintained and because of this, we are constantly sick,” the latest letter reads. “We demand freedom, a fair trial, and for our rights to be respected.” The first three letters released by striking detainees also listed a series of demands: a meeting with New Jersey’s governor, Mikie Sherrill, who has come under fire from protesters; the release of sick and elderly detainees; for immigration cases to proceed more quickly; and for immigration officials to stop pressuring them to sign documents agreeing to be deported. The Department of Homeland Security (DHS) did not respond to detailed requests for comment. Meanwhile, amid national attention on Delaney Hall, DHS officials have repeatedly claimed that people they arrest are “criminals” and the “worst of the worst”. But a recent data review of ICE’s own data by Austin Kocher, an assistant research professor at Syracuse University and an immigration data and policy expert, found that claims by DHS are wildly overstated. According to the latest data from mid-March, 88% of immigrants detained in Delaney Hall at the time had no criminal conviction and just over 70% had no criminal history whatsoever. And the majority of those with criminal convictions were charged with low-level offenses, Kocher reports. Despite most alleged immigration violations involving civil not criminal law, the second Trump administration has detained record numbers of people, deporting many, including people whose US papers were no longer accepted. The largest private prison operator in the US, GEO Group, operates Delaney Hall and currently has a one-billion dollar contract to run it for 15 years. “The food is not that good, the bathrooms are dirty,” said Maria Santos, whose husband is detained inside. Santos was also allowed to visit him on Tuesday afternoon. The hunger and labor strike began on 22 May. Santos’s husband, she told the Guardian, has not participated in the strike out of fear of retaliation by GEO Group guards and ICE officials. “We don’t know if they can take it [out] against them or something,” she said. The striking detainees have already accused DHS and GEO Group officials of retaliation. “Since the strike began, we have been subjected to reprisals, discrimination, mockery, mistreatment, and threats, mainly from ‘GEO’ [Group] staff,” the latest letter reads. “They constantly threaten to deport us, transfer us to punishment units, and move us from one detention center to another; they take photos of us in the dormitories without our consent and tell us that we have no rights here.” “GEO strongly refutes these allegations,” a company spokesperson said, in response to a request for comment. “The support services GEO provides include around-the-clock access to medical care, in-person and virtual legal and family visitation, general and legal library access, translation services, dietician-approved meals, religious and specialty diets, recreational amenities, and opportunities to practice their religious beliefs.” GEO Group referred all questions about Guerra’s case to the DHS. Gabriela Soto, whose husband Martin was detained in Delaney and participated in the strike has helped organize protests outside the facility. “Once I started going to the visits and started seeing these people tell their stories, it made me so angry that they don’t have a voice,” Soto told the Guardian, the anger in her voice palpable. “What really boiled me over was the fact that they got served worms for food. It got me so pissed that I needed to do something. We needed their voices to be heard, which is why the protest started in the first place.” Martin Soto was arrested by ICE in early February when getting diapers for their child. “The conditions in there are horrible. The food stinks. It is expired, it is chunky. They just got served worms, crawling on their plates. You don’t even give an animal worms,” Soto added. The DHS has repeatedly denied allegations about conditions related to Delaney Hall and denied that there are any “sub-prime” conditions to be found there – as they have denied similar allegations about other ICE detention facilities. On 24 May, lawmakers and Sherrill arrived at the facility for an oversight visit. When Soto and others attempted to prevent Martin Soto’s transfer, ICE officers pepper-sprayed the protesters, including US senator Andy Kim. Martin Soto was transferred to another ICE detention center, but the ordeal drew more protesters to Delaney Hall. Meanwhile, Guerra’s relative has not visited him since the strike began, nor since family visitation was reintroduced last Sunday. Facility officials and police on Tuesday were asking relatives to provide their full names for visitation, making Guerra’s relative nervous the information would be shared with ICE. “What he told me made me very sad,” the relative said when describing the earlier visit after Guerra’s…",
    "body_chars": 10350,
    "body_truncated": true,
    "url": "https://www.theguardian.com/us-news/2026/jun/07/ice-jail-new-jersey-delaney-hall",
    "section": "US news",
    "published": "2026-06-06T16:00:08Z",
    "source": "Guardian"
  },
  {
    "title": "Ministers may try to curb spread of misinformation during social unrest",
    "summary": "Technology secretary says she is ‘very concerned’ about role of social media but will not be ‘bullied off’ X",
    "body": "The government is considering fresh action to halt the spread of misinformation during public crises, Liz Kendall has said, insisting she will not be “bullied off” Elon Musk’s X. The technology secretary was speaking after rioting broke out in Southampton over the police response to the fatal stabbing of Henry Nowak, a case about which Musk has repeatedly posted. She said she was “very concerned” about the role of social media platforms in times of unrest, adding: “I definitely think, particularly during moments of crisis and disorder and when public safety is important, we need to look at what more we can do.” Kendall pointed to a report last year from the Commons science, innovation and technology committee that called for Ofcom to implement “crisis response protocols” to hold platforms responsible for misinformation. The media regulator has consulted on the issue, with more details expected to be announced this month. The committee launched its investigation after the riots of summer 2024, when misinformation spread quickly after the murder of three girls at a dance class in Southport. Its report found that “misleading and hateful messaging proliferated rapidly online, amplified by the recommendation algorithms of social media companies”. Kendall said the government was “looking at not only boosting trusted sources of information, which I think is extremely important and there’s probably more we could do there. But also, you know, enabling people to reset their algorithms.” She added: “I think lots of people think they see this stuff coming towards them. And it should be much easier for people to say ‘let’s have a reset’ – so I am looking at that again.” Chi Onwurah, the chair of the committee, said: “The government must do more to stop the spread of misinformation online. My committee’s report found the Online Safety Act to be woefully inadequate and riddled with regulatory gaps – yet most of our recommendations for how to improve this were rejected. “Since then, the secretary of state has told my committee that the report was ‘excellent’. However, a year after its publication, no progress has been made to update the OSA. Our current regulation just isn’t up to scratch.” On Thursday, Keir Starmer accused Musk of “interfering in our politics”. However, Kendall said: “I understand my colleagues, why they don’t want to be there [on social media], but I didn’t want to be bullied off any platform. “I’m going to get the government’s message out; hopefully to some people who want to hear it and definitely to those who don’t. Because I want to say that this government stands for hope and not hate.” Musk has repeatedly highlighted the Nowak case to his 240m followers on X. One of his posts, sharing comments from the far-right MP Rupert Lowe, simply said “RAGE”. It was viewed more than 25m times. Kendall’s last post on X, about a visit to Liverpool University to highlight taxpayer backing for innovation, was viewed 5,500 times and shared eight times. The Labour MP Jess Asato is taking legal action against Musk’s xAI company over demeaning sexualised material created by its Grok AI tool that spread across X earlier this year. The prime minister praised Asato’s decision on Thursday, saying she was “absolutely right” to take action. Analysis by the human rights group Amnesty last year claimed X’s algorithms had contributed to what it called a “staggering amplification of hate” after the Southport murders. The Commons committee said the Online Safety Act, which was not fully in force at the time of the 2024 riots, did not contain adequate measures to contain misinformation. Kendall said: “I think from the initial idea and discussion to implementation [of the act] was eight years. It is a long time. It’s too long. It’s too slow. This technology is developing so rapidly. MPs vote on a finance bill every year. It can’t be beyond the wit of man or even womankind to do things more quickly.”",
    "body_chars": 3948,
    "body_truncated": false,
    "url": "https://www.theguardian.com/politics/2026/jun/06/ministers-may-curb-misinformation-musk-x-liz-kendall",
    "section": "Politics",
    "published": "2026-06-06T16:00:08Z",
    "source": "Guardian"
  },
  {
    "title": "Pope Leo calls for leaders to reject polarisation as he begins Spanish tour",
    "summary": "Pontiff to make marginalised a focus of first papal visit since 2011 including meeting with migrants in the Canaries",
    "body": "Pope Leo has urged political leaders to seek unity, rather than divide their populations for political gain, and said they must fight for peace, in the opening speech of his tour in Spain. The pope has made the marginalised a focus of his visit – his first tour of an EU country, apart from Italy – including meeting homeless people in Madrid and migrants in the Canary Islands. The pope, who has clashed with the US president, Donald Trump, over his immigration policies and war with Iran, said his visit was aimed at setting an example of respecting “every human being”. He was also due to meet survivors of sexual abuse by clergy in the Spanish Catholic church – an institution that is only now confronting its history of papered-over abuse. Leo said he would meet a few survivors, admitting that “abuses are still an open wound”. Thousands of people gathered in the streets of Madrid to greet the pontiff, who toured the city in the popemobile. It is the first time a pope has visited Spain since 2011. There has been a resurgence over recent years in Spain in the number of those who identify as Catholics, with 28.8% of young people identifying as such in 2025, compared with 17.6% in 2010. The pope is scheduled to give 20 speeches during his tour, with themes emphasising empathy for migrants, anti-demagoguery, and acknowledging what Leo said was a world crying “from its depths for peace”. “Today, the temptation to gain popularity by fanning the flames of polarisation seems to have grown rather than diminished, and human dignity continues to be violated,” he said in a speech attended by King Felipe VI at the royal palace in Madrid. “I invite everyone to set aside the divisive and polarising narratives of your societal reality and history so as to overcome sterile simplifications through the fruitful appreciation of complexity.” He suggested that technology and social media were playing a role in deepening divisions and preventing societal introspection. Leo recently released a letter focused on the dangers of artificial intelligence, suggesting that humanity was at a moral crossroads as AI technology rocketed forward. He pointed towards Spain as a country with a history of coexistence between different religions, referencing how Christians, Muslims and Jews lived together peacefully in medieval times and how they cooperated in their respective languages to advance knowledge. “Your own history suggests that a culture of encounter, not confrontation, is what fosters stability and prosperity. In reality, the message of peace, which at present, unfortunately, strikes some as naive and others as confrontational, is welcomed by those who do not shut themselves off in preconceived ideologies, but are rather open to the truth,” he said. Spain, under its socialist prime minister, Pedro Sánchez, has launched a mass amnesty programme providing about half a million immigrants with a pathway to legal residency. Spain’s policies are a contrast to much of Europe and the wider western world, which have seen a rise in xenophobia and anti-migration policies in recent years. In addition to meeting migrants in the Canary Islands, he will meet survivors of sexual abuse by Catholic clergy. Spain’s human rights ombudsman estimated in a 2023 report that there were hundreds of thousands of survivors of abuse over past decades. King Felipe told Leo, in an apparent reference to a recently launched church-state reparations system for some survivors of clerical abuse: “Your clarity and firmness, which I also wish to acknowledge, are essential in the process of healing and repairing the harm inflicted. They are essential for the victims, for the faithful, for the church and for society.” The Spanish church also suggested that the pope might meet the Puerto Rican singer Bad Bunny, who is in the middle of a 10-date run of performances in Madrid. Leo joked that he faced an uphill battle when it came to competing with the pop star for young people’s interest. “If they were confronted with the question: do they want to see Bad Bunny or do they want to see the pope, I think many will go to see Bad Bunny,” he said on his flight from Rome, before adding: “But I think there will also be a few here to see the pope.”",
    "body_chars": 4242,
    "body_truncated": false,
    "url": "https://www.theguardian.com/world/2026/jun/06/pope-leo-xiv-spain-tour-madrid-catholic-church",
    "section": "World news",
    "published": "2026-06-06T15:54:05Z",
    "source": "Guardian"
  },
  {
    "title": "Second flesh-eating screwworm infection reported in cattle in Texas",
    "summary": "Governor issues disaster declaration as agencies move to stop spread of parasite, including release of sterile flies",
    "body": "A second case of the flesh-eating screwworm fly has been confirmed in Texas by the US Department of Agriculture (USDA), days after an initial case in a one-year-old calf set off an aggressive response to stop the spread of the parasite in the dominant cattle-producing state. Texas’s governor, Greg Abbott, said on Friday that state officials were working with the federal government to slow the spread of the fly and the infestations caused by larvae that feed on the living flesh of warm-blooded animals and humans. Officials are dispersing millions of sterile screwworm flies in the vicinity of where the twin infections were found about five miles apart in Zavala county, south-west of San Antonio. Those sterile male flies would prevent wild female flies from reproducing. The infections of the new world screwworm (NWS) are the first detected in the US since the 1960s. The USDA confirmed the second case. The first case was confirmed by the Texas animal health commission (TAHC) on Wednesday after NWS was detected in a three-week-old calf with an umbilical lesion. “This is the first detection of NWS in Texas since northward progression from Central America was observed in 2023,” the commission said in a news release, adding that an infested zone has been established in the area. The commission also said that animal movement restrictions were in effect to prevent further spread of the pest. According to the USDA, the US food supply is safe, and it noted that NWS do not infest meat, fruits, vegetables or other food sources. NWS are parasitic larvae or maggots of the NWS fly (Cochliomyia hominivorax). They cause a painful condition called NWS myiasis. When the fly’s eggs hatch, larvae burrow through living flesh, killing their host if left untreated. “TAHC has been actively preparing for a resurgence of NWS for over two years,” the commission’s director, Dr Bud Dinges, said. “We are putting these preparations into action, and we encourage all animal owners and caretakers to continue to remain vigilant for the presence of larvae in animal wounds and immediately report any suspicions.” The TAHC said that the introduction of sterile flies, when combined with enhanced surveillance, movement restrictions, prompt treatment of wounds, and education and outreach efforts, “is a proven and effective tool for controlling and eradicating this pest”. Abbott also issued a statewide disaster declaration and warned that it is likely to be “an extraordinarily challenging summer” for infected areas. “We’re in the season for spread,” the governor said. The USDA discovered the second infestation “after testing a number of suspect cases”, the agency’s animal and plant health inspection service said in a press release. The detection of the parasite is a blow to US cattle ranchers. A widespread resurgence now could pose a significant economic threat in Texas through animal deaths as well as higher ⁠labor and treatment costs. For more than a year as the disease moved north, the US-Mexico border has been closed to live cattle imports, causing the $100bn US beef industry to contract to a 75-year low. The US formerly imported more than 1m cattle a year from Mexico, representing about 4% to 5% of all cattle sold for US beef production, according to industry data. On Friday, Canada’s food inspection agency announced a temporary ban on livestock from Texas after the infections were detected. Cows and horses that were in Texas anytime within 21 days before crossing the border into Canada would not be accepted into the country, an agency news release said. Canadian officials noted that NWS is unlikely to become a problem in the country because of its colder climate – but they warned farmers to monitor livestock for wounds and any cut that is “accompanied by discharge or foul odor”.",
    "body_chars": 3809,
    "body_truncated": false,
    "url": "https://www.theguardian.com/us-news/2026/jun/06/second-flesh-eating-screwworm-infection-texas",
    "section": "US news",
    "published": "2026-06-06T14:00:41Z",
    "source": "Guardian"
  },
  {
    "title": "Party poopers: New Yorkers sniff at pet owners leaving behind animal waste",
    "summary": "Increase in complaints about the hazardous eye sore has prompted city to take action to curb irresponsible owners",
    "body": "Kumar Satya has lived in Manhattan’s Washington Heights neighborhood since 2017 and said he loves the local parks, how people talk on the street and the sound of children “screaming, playing”. “It was a very hot day two weeks ago, and you noticed tiny children just offering lemonade to people,” said Satya, a physician who has a 13-year-old son. But in recent years, the neighborhood has become inundated with a hazardous eyesore: dog poop. This year, at least 175 people from the community board – a governmental body – that includes Washington Heights, filed dog waste complaints with the city; the second worst board has seen 116 complaints, according to the city. “I grew up in India, where [open] defecation is a problem,” Satya said. “This reminds me of that.” While the waste has been especially bad in Washington Heights, other neighborhoods and cities have also recently seen an uptick in poop left on the ground – prompting the city to take action. New York officials have tried to address the problem through enforcement of a law that fines people for not picking up poop, but they say that catching irresponsible dog owners is very difficult. Now, city council members have introduced a handful of bills they hope will encourage dog owners to become better neighbors and make sidewalks less treacherous. “It’s a quality-of-life issue, which just makes people angry that people are not picking up after their dogs,” said Julie Menin, the New York City council speaker. “We are not looking to penalize anyone here; we are just looking to encourage people to do the right thing.” People failing to pick up after dogs is, of course, not a new issue, but US residents and public officials say the problem has gotten worse in recent years. That appears to be, at least in part, because pet ownership has steadily increased over the past few decades – particularly during the Covid-19 pandemic, when people became more isolated. In 2016, there were 76 million pet dogs in the United States, according to the American Veterinary Medical Association. In 2021, there were almost 88 million. That has correlated with an increase in complaints filed about people not picking up dog waste. The Guardian requested data from New York City on the number of annual complaints concerning dog waste since 2019, but Ray Legendre, a spokesperson for the office of technology and innovation, only provided numbers for 2022 onwards. Asked why he declined to provide data from 2019 to 2021, Legendre did not respond. But there has been a steady uptick even after the pandemic. In 2022, the city received 2,100 complaints. In 2025, the city received 2,659. And this year, the city has already received more than 2,400. Legendre attributed the spike to the blizzard. The subsequent snow melt revealed weeks of dog waste. Other cities have faced the same problem. In San Francisco, the average neighborhood saw a 400% increase in complaints to the city’s 311 hotline about dog or human waste between 2012 and 2021, the San Francisco Chronicle reported. In the United Kingdom, so many people started leaving poop bags on branches during the pandemic that the Daily Record labeled the scene the “the hanging gardens of jobbylon”. (Jobby is a British nickname for poop.) Dog excrement not only looks bad and irritates those who step in it, but also can harm public health because it contains bacteria, pathogens and parasites, which during heavy rain can contaminate local water. Part of the problem is people simply not paying attention when walking their dogs, said Harry Berberian, a Brooklyn resident who has a dog, Stevie, and works for a dog rescue organization, the Sato Project. “I am one of those neighbors who goes out of my way to say something because I often observe people who are either on a phone call or busy taking care of something else,” Berberian said of walking in Fort Greene Park. Even though he tries to be polite, “most people are not very pleased”. Other people just don’t care about littering. Crystal Lee and her neighbors in Brooklyn’s Bedford-Stuyvesant neighborhood have witnessed the same person walking two dogs, repeatedly letting them poop on the sidewalk and then casually walking away. They have captured him on camera and confronted him about picking up the poop. “He has basically said, ‘F-you,’” said Lee, a nurse and owner of a dog, Snowboard. In one case, a resident picked up the poop, followed him home and dropped it off at his door. Lee also submitted screenshots of the video in a complaint to the city in May. The next day, the department of sanitation stated that it had investigated the complaint and found no violation. “It’s just incredibly frustrating,” Lee said. “Either I just accept that I’m going to continue to have to pick up after his dogs when they land in front of my property, or I can go nuclear and be like, let’s post pictures of this guy, this repeat offender, and see if he has any shame.” New York City has seen the uptick in waste even though it was a trailblazer when, in 1978, it passed the “Pooper-Scooper Law” and became the first major US city to require its citizens to pick up after the pets. People who fail to do so can be fined up to $250. But it’s difficult to enforce. In 2025, the sanitation department conducted patrols in Washington Heights, Harlem, Morningside Heights and Flatbush – in response to 311 complaints – but could not catch anyone, according to a spokesperson. The city issued a total of two summons last year. “The chances of someone not picking up after their dog while an enforcement officer is watching is very, very slim,” Vincent Gragnani, press secretary for the sanitation department, stated in an email. Instead, city council members recently introduced the Safe and Clean Outdoor Ownership Practices (Scoop) Act, which contains legislation that would require agencies to regularly fill waste bag dispensers next to litter baskets, install signs about penalties for dog waste, establish a pilot program to collect dog feces as part of a composting program and conduct an outreach campaign about the dangers of failing to remove the waste, among other measures. “There is no excuse when there are going to be these dog waste bags on litter baskets,” Menin, the council speaker, said. “It’s not an enforcement approach. It’s an education, awareness and deterrent approach.” Diane O’Dwyer, a frustrated Washington Heights resident, wants the city to do more to punish negligent dog owners. She once saw a woman step out of her convertible, throw a poop bag in the street and enter a bodega. O’Dwyer, a home healthcare aide who was walking her dogs, threw the bag in the car and ran. She thinks enforcement is possible and pointed to aggressive efforts in the United Kingdom, where she once lived. In Liverpool, the city hired a contractor to crack down on littering and handed out 45 fines in July 2025, the BBC reported. “I know it’s a tough city to deal with,” O’Dwyer said of New York, “but don’t have fines posted and not enforce them.”",
    "body_chars": 7028,
    "body_truncated": false,
    "url": "https://www.theguardian.com/us-news/2026/jun/06/dog-poop-new-york-city-sidewalks",
    "section": "US news",
    "published": "2026-06-06T14:00:09Z",
    "source": "Guardian"
  },
  {
    "title": "Trump cries ‘steal’ over slow California vote count, but anti-fraud system works, say experts",
    "summary": "State’s tortoise-like pace is byproduct of system of verifications and opportunities for voters to fix errors",
    "body": "California’s slow vote counting has frustrated political observers eagerly awaiting results, and handed Donald Trump and others an opportunity to claim “election rigging”. But experts say the system is working as designed: to protect against fraud and assure every vote is counted. Within a day of the polls closing in California’s primary election this week, Trump started accusing Democrats of “trying to steal” the elections for the state’s governor and the mayor of Los Angeles. The justice department sent a federal prosecutor to observe the ballot-counting process in Los Angeles this week. Republicans have lobbed such allegations against California for years, pointing to the state’s slowness in tallying ballots and the shifting results over the course of the counting as evidence of vote manipulation. Prominent Democrats, including outgoing governor Gavin Newsom, are increasingly fretting that the state’s tortoise-like pace is becoming a liability for public confidence in elections in an era where conspiracy theories spread quickly through social media and can emanate straight from the White House. But California’s vote-counting pace is actually a byproduct of a system of redundant verifications and opportunities for voters to fix errors. Every voter in California receives a mail-in ballot, and a vast majority of voters vote via mail. The signatures on those ballots are verified electronically and by human observers. When a ballot contains errors, the state gives voters 22 days to “cure” it. The result is a system that is both highly accurate and resistant to letting small oversights devolve into trashed ballots. But in the state with the most registered voters by far, it comes at the cost of speed. “There’s not a lot of people I know who would say: ‘Nah, I would rather have known who won the race faster than have my vote count,’” said Paul Mitchell, vice-president of the voter data firm Political Data Inc. “So what’s the rush? The focus should be making voting as easy as possible.” “The only people who complain about it are the people who lose,” Mitchell added. “The conspiracy around it is really a conservative thing.” Still, experts see obvious ways the system could improve. The legislature could invest the money that counties need to pay for staff, equipment and space to process ballots faster. The state assembly reduced the number of days a voter has to “cure” ballot errors from 26 to 22 last year. Cutting it further could substantially shorten wait times without severely inconveniencing voters, said Lisa Bryant, a political scientist at California State University, Fresno. “California is very liberal on how much time they give people to cure those ballots,” Bryant said. “I think California could tighten up those timelines. That could help speed up the timelines without losing a lot.” Election day itself creates the biggest bottleneck. A majority of the state’s voters use mail-in ballots for convenience, and voters have until election day itself to post them. Because many people still feel more secure depositing ballots at a polling site, a large segment of voters walk them in on election day instead of mailing them. But those votes can’t be counted until after election day, and they’re routed through a more time-consuming process. The election day bottleneck was exacerbated this year by a uniquely tight gubernatorial race, in which many voters waited as long as possible to vote. Some political observers hope that voters themselves can alleviate the problem by developing a culture of not waiting until the last minute to mail or walk in their ballots. But dozens of counties have implemented a system in which voters open their walked-in ballots and cast them at the site, speeding up the process. “It’s a great benefit for voters because they know their ballot has been counted,” said Kim Alexander, president of the California Voter Foundation. “They can walk away with confidence.” California should pursue changes like those to preserve voter confidence, Alexander said. Waiting around for weeks to find out who won an election can erode trust in government, even if the delays have a clear explanation. Regardless of whether or how California’s voting system changes, the state is likely to remain a target of specious allegations of fraud for the simple reason that it’s the site of competitive elections with national impact in a polarized era where a vocal minority has the capacity to spread disinformation quickly. “Corrective messages don’t tend to go viral,” Bryant said. “It’s like hiking the Grand Canyon. They tell you to account for twice as much time going up as going down. It’s at least that much time trying to combat misinformation.”",
    "body_chars": 4722,
    "body_truncated": false,
    "url": "https://www.theguardian.com/us-news/2026/jun/06/california-slow-vote-count",
    "section": "US news",
    "published": "2026-06-06T14:00:08Z",
    "source": "Guardian"
  },
  {
    "title": "No Black jurors selected for murder trial over killing at 2025 Texas high school",
    "summary": "Karmelo Anthony, who is Black, is accused of stabbing Austin Metcalf, who was white, at track meet in an affluent Dallas suburb",
    "body": "After a 2025 high school track meet in Frisco, Texas, ended with one student dead and another accused of murder, Karmelo Anthony, then 17, was indicted on first-degree murder in the fatal stabbing of Austin Metcalf, 17. Social media posts about the death divided the case into racial lines, sparking national outrage. Anthony, who is being tried as an adult, is Black; Metcalf was white. This week marked the beginning of Anthony’s murder trial. After three days of juror selection, attorneys selected 12 jurors and six alternates for the trial, narrowed down from 600 initial summonses. None of the jurors are Black. Defense lawyers accused prosecutors of improperly striking the only three remaining Black prospective jurors, according to a local NBC affiliate. The district judge John Roach, however, accepted the state’s explanation that they were removed because they are educators. “The prosecution used its final strikes to remove the remaining qualified Black jurors from the jury pool, raising serious concerns about fairness and equal justice,” the Next Generation Action Network civil rights organization, based in Dallas, wrote in a post on X on Wednesday. “We respect the court, but we will not remain silent … Every person deserves a fair trial and confidence that justice is being administered without bias. We are calling on the court to ensure Mr Anthony’s constitutional rights are fully protected.” The teens went to different high schools in the same affluent Dallas suburb. They were both at the 11-5A championship district track meet during a rainstorm that turned into a downpour. Witnesses said that the incident began when Anthony sat under a tent belonging to Metcalf’s team. According to the arrest report, witnesses said that Anthony allegedly reached inside his bag and said, “Touch me and see what happens.” Metcalf grabbed Anthony and, according to a witness, Anthony allegedly pulled a knife from his bag, stabbed Metcalf and ran away. In a packed courtroom on Thursday, jurors were shown grainy surveillance footage of the attack, taken from across the field. The video shows a person, whom the state identified as Anthony, entering the tent . There are quick movements – prosecutors told jurors that that was Metcalf, trying to push Anthony out of the tent. Later, Anthony exits the tent, after appearing to stab Metcalf, and runs away. The defense on Thursday said that there were differing accounts as to what was said in the moments leading to the stabbing. Anthony’s attorney, Mike Howard, said Anthony went to the tent to get away from the rain after seeing someone he recognized. Everyone else at the tent attended the same high school as Metcalf. There, the defense said, Metcalf and his twin brother, who are about 6ft 1in and 213lb, confronted Anthony, who is 5ft 8in and about 130lb. Metcalf made first contact and “grabs, shoves, pushes” Anthony, according to the defense. Then Anthony put his hand in his bag and made a split-second decision to act. Howard claimed that the teen acted in self-defense, reacting to “fear and chaos”, while a prosecutor said that Metcalf was stabbed in a “sneak, surprise attack”. Jurors heard from eyewitnesses, including coaches and an athletic trainer. “You want your kids in your camp,” said Vincent Hooper, the track and football coach at the Heritage high school and a witness for the state, of track tents. The defense noted that Centennial, Anthony’s high school, did not have a tent at the meet. Tiffany Whiteaker, Memorial high school’s athletic trainer and a witness for the prosecution, said that there was a lot of confusion on the day of the attack because of the rain. Some students were on the field, while others were on the bus and others, still, under the tent. Hooper held Anthony after the stabbing. He testified that he told Anthony that his entire life would change if Metcalf died. “He’s not going to die,” Anthony said, according to Hooper. Before the second day of testimony began on Friday morning, three people were removed from the Collin county courthouse. On Friday, a Frisco school resource officer, Eduardo Cortez, testified that Anthony was cooperative after the incident. He said that he handcuffed Anthony and radioed, “I have the alleged suspect detained.” Cortez said that Anthony then said: “I am not alleged. I did it.” Cortez recalled that without being prompted Anthony said: “He put his hands on me. I told him not to. He put his hands on me.” While being placed in the police car, Anthony asked if Metcalf was OK. Jurors watched body-cam footage of the events that Cortez detailed. As Anthony is walking towards the car, the video depicts him sobbing and saying: “He put his hands on me.” Moments later, while answering questions, Anthony is no longer crying. Cortez also testified that weapons were strictly prohibited on Frisco school grounds. Judge Roach has imposed a gag order in the case and barred any electronics, including cellphones, from the courtroom during the trial. The trial is expected to last about two weeks. Anthony, if convicted, faces five years to life in prison. • The headline of this article was amended on 6 June 2026 to reflect that no Black people were selected for the jury, instead of the jury being all white as it originally stated.",
    "body_chars": 5286,
    "body_truncated": false,
    "url": "https://www.theguardian.com/us-news/2026/jun/06/trial-killing-2025-texas-high-school-track-meet",
    "section": "US news",
    "published": "2026-06-06T13:00:06Z",
    "source": "Guardian"
  },
  {
    "title": "UK’s fragile heirloom: ceramics sector calls for more help to save ‘vital industry’",
    "summary": "Brands such as Portmeirion in Stoke welcome £120m package but seek further support to avert fresh closures",
    "body": "On the floor of Portmeirion’s factory in Staffordshire, staff are hard at work as clays are moulded, glazed and fired – an intricate process requiring precision and specialist skills honed over years of practice – to manufacture the company’s array of tableware. Portmeirion, a homeware brand founded in 1960 that employs 433 people, is based in Stoke-on-Trent, at the heart of British ceramics. The centuries-old craft is so integral to the area’s identity that the six federated towns that make up the Staffordshire city are known as the Potteries. “All my family were in the industry,” says Sam Pearce, the company’s chief operating officer. “It’s a really important part of the heritage of the city.” The UK ceramics sector employs 20,000 people, half of them in the West Midlands, and is regarded as an indispensable to the economy. Not only does it manufacture household essentials such as crockery, bathroom fittings, tiles and bricks, but also defence, security and technology components ranging from microchips to missiles. But this national heirloom is starting to crack as it suffers the blows of international competition, rising labour expenses and the soaring cost of energy, which leapt after Russia’s invasion of Ukraine and has again been driven up by the US-Israeli conflict with Iran. Illustrious names in the region have gone under or are teetering on the brink. In February last year, Royal Stafford went bust after nearly 200 years and Heraldic Pottery closed the same month. The world-renowned Wedgwood was forced to freeze production at its factory for 90 days, only restarting in January, and Derbyshire-based Denby, established in 1809, called in administrators on 31 March, with the group blaming escalating employment and energy costs. “The sector as such has been under huge pressure – there’s no denying that,” says Michael Scheepers, Portmeirion’s recently appointed chief executive. “I think everybody who has seen recent news of companies struggling and brands disappearing over time can see how it has impacted the overall sector.” The chancellor, Rachel Reeves, said the industry underpinned “our economic resilience” when she announced a £120m support package to support energy efficiency, decarbonisation and long-term competitiveness last month. The trade body Ceramics UK will work with civil servants on the design and implementation of the scheme. Rob Flello, the chief executive of Ceramics UK, says rising energy costs are central to the financial difficulties. Production processes require prolonged firing temperatures typically above 1,000C, but the cost of gas to power furnaces has soared, with UK month-ahead prices hovering around 118p a therm – 50% up on the 78.50p the day before the Iran war began. However, he argues high prices have been compounded by the government’s target to reach net zero emissions by 2050. That policy, championed by the energy secretary, Ed Miliband, came under fire in Tony Blair’s wide-ranging attack on Keir Starmer’s government last month. The former prime minister urged the government to “prioritise cheaper energy and electrification over net zero and use what is left of our North Sea oil and gas” – an intervention criticised as “bizarre” by experts in the face of energy and climate crises. However, it appears to resonate with some ceramics-sector leaders. “It’s no good us being zero carbon [in the] UK in 2030 if that’s because we don’t manufacture anything in the UK,” Flello says. He wants the government to “decarbonise sensibly rather than decarbonising by deindustrialisation, which is the path we’re on at the moment”. “Energy is much much more expensive in the UK than in competitor countries,” he adds. “Our brickmakers pay effectively a carbon tax under the UK emissions trading scheme. Imports from Turkey, China and India don’t have to pay carbon tax. So the odds are very much stacked against British industry.” Alex Patrick-Smith, the executive chair of Dreadnought Tiles, a brick and clay roof tile manufacturer based in the West Midlands, agrees, saying Blair is “pushing the right buttons” and the current targets on net zero are “not realistic”. “I’m a great supporter of decarbonising. I do see global warming as a big threat,” he says, but adds: “We’ve lost a lot of our supply chain in our industry. The number of businesses that are left are dwindling in our industry and it just comes to a point where you’ve just got to stop. “This is strategically important for the country … If things get really tough in the geopolitical world and you can’t repair your bridges because you can’t make engineering bricks in this country any more, you’re expecting to import them from overseas. In doing so, all you’re doing is exporting your carbon to somewhere else – it’s not improving the global situation.” Flello says the ceramics industry is committed to decarbonising and has spent £750m on initiatives to do so, but it is inherently energy hungry and therefore one of the hardest to wean off fossil fuels. Patrick-Smith says his company has spent “hundreds of thousands” on energy efficiencies, including kiln upgrades and a heat recovery scheme. However, he says many of those investments were “eye-wateringly expensive and the returns are just not there”. In the hopes of addressing rocketing energy costs, all three industry leaders called on the government to extend eligibility to the British Industry Supercharger and British Industrial Competitiveness Scheme (BICS) – which provide relief from electricity costs for firms in areas such as steel and chemicals. When Reeves beefed up the BICS scheme in April in response to Iran war pressures, expanding the number of firms covered to 10,000, ceramics companies asked why they had been left out. Nearly 90,000 people have since signed a petition asking for the sector to be included. A government spokesperson said: “Manufacturing industries like ceramics are vital to the UK’s success and essential for growth, but we recognise the challenges they are facing, including on the cost of energy.” They highlighted the £120m support already announced for the sector, adding: “We continue to work closely with the industry to ensure we’re doing what we can to help them through tough times.” Ceramics are not only fundamental the UK’s economic resilience, the industry leaders argue, but also to the heritage and economy of the West Midlands. Flello, who was a Labour MP for Stoke-on-Trent North from 2005 to 2017, says: “There was a saying locally that you either work in the pits or the pots. Pretty much everybody you knew worked either in one of those two. “Over the last 50, 60 years, the industry has dramatically contracted – rather than every town now having a brickworks there are probably about 36 across the UK.” Yet despite such decline, the industry still has passionate backers. The heritage brand Moorcroft returned to production in September after being saved from liquidation by the grandson of its founder. And this week rumours were swirling of a possible rescue for Denby, after Sky News reported that Home Bargains, one of the UK’s biggest homeware retailers, was pursuing an acquisition for its name and other assets. Scheepers says Portmeirion is determined to increase its production in the UK: “If we have clear, targeted support, I think that would be invaluable.” Flello also says that, despite the challenges, there are glimmers of hope. In particular, he says Reeves’s support package could be the springboard to signal “the industry can stop declining and start growing again”. He says: “There is definitely hope and with the £120m that’s probably the greatest cause of optimism. It all depends now on how the programme is put together. It does need some other things coming in behind it, but this is really a positive development.” Additional reporting Jasper Jolly",
    "body_chars": 7855,
    "body_truncated": false,
    "url": "https://www.theguardian.com/business/2026/jun/06/uk-ceramics-industry-support-package-revival-portmeirion-stoke",
    "section": "Business",
    "published": "2026-06-06T13:00:05Z",
    "source": "Guardian"
  },
  {
    "title": "More Republicans are breaking with Trump. Is it conscience or politics?",
    "summary": "Congressional Democrats say GOP majority is unraveling, but moves may in fact be aimed at retaining power",
    "body": "The wrath of Donald Trump has kept congressional Republicans in line for much of his second term thus far. But as the November midterm elections draw closer, the president’s allies in the Senate and House of Representatives appear increasingly willing to defy a president who appears to have asked lawmakers for too much in some areas and too little in others, all while the public sours on his administration. In both chambers, small groups of Republicans have in recent weeks joined with Democrats to advance resolutions requiring that Trump receive Congress’s permission before continuing hostilities against Iran. Republican dissidents in the House helped pass another round of aid for Ukraine, as well as an effort to protect Haitians from deportation. In the Senate, a critical mass of Republican senators has given Trump’s nominee for director of national intelligence, Bill Pulte, a cold reception. In the wee hours of Friday morning, the Republican majority passed a $70bn bill that will ensure the federal agencies leading Trump’s mass deportation campaign have the money they need to operate through the duration of his term. But that effort was delayed by concerns over an attempt to include $1bn in spending to secure the ballroom Trump is building at the White House, which was ultimately dropped after it became clear the money could imperil the bill’s chances of passage. Even as voting on the measure began in the Senate on Thursday, Republicans spent hours considering, and ultimately rejecting, amendments that could have permanently barred the president from using $1.8bn in an “anti-weaponization” fund to pay his allies. Internal disagreements are nothing new for congressional majorities as they consider a president’s asks, but Republicans appear bedeviled by the complications of their three-seat majority in the Senate, and historically slim hold on the House. While they managed to enact a major domestic policy bill less than six months after Trump’s inauguration, the president has made few serious asks of Congress in the months since, leaving lawmakers to navigate shutdowns instigated by Democrats in protest of his policies and the brouhaha over the government’s investigation into convicted sex trafficker Jeffrey Epstein. Trump has made no apologies for his apparent disengagement with the concerns of congressional Republicans, saying at a recent cabinet meeting: “I don’t care about the midterms.” Were the GOP’s majorities bigger, protest votes and uncooperative members would not be such a big deal. Instead, they have wound up tilting votes against the wishes of the Senate majority leader, John Thune, and the House speaker, Mike Johnson, who regularly has to bat away questions about whether he is actually in control of his chamber. The open dissent has proven a boon for congressional Democrats, who have seized on the fractiousness as proof that the Republican majority is already unraveling. Trump’s approval ratings are consistently low, gas prices remain high, polls show voters believe the conflict with Iran is a poor choice and Democrats are leading by various amounts in surveys of the generic ballot, an important indicator of their chances to take back control of Congress in the midterms. “Republicans right now, in both the House and the Senate, are in freefall,” the House minority leader, Hakeem Jeffries, said on MS Now last month, after Johnson canceled a vote on the Iran war powers resolution. When it finally came up for a vote this week, the resolution passed with the support of four Republicans and all Democrats. Those trends may indeed have been motivating the defections by some lawmakers. Two of the Republicans who backed the war powers resolution in the House, Tom Barrett of Michigan and Brian Fitzpatrick of Pennsylvania, are top targets of Democrats in the midterms, as is Susan Collins, the Maine senator who was one of four Republicans who voted to advance a similar measure. Many of the 19 Republican-aligned House lawmakers who voted for Ukraine aid, and the 11 who backed continued temporary protected status for Haitian immigrants, also face tough re-election contests. The president’s threats against lawmakers who defy him has the knock-on effect of creating new obstacles in Congress. Last year, the North Carolina senator Thom Tillis opted to retire, after drawing Trump’s ire for refusing to support the One Big Beautiful Bill Act, the president’s main domestic policy. He has since become a prominent critic of what he sees as poor choices being made by the Trump’s advisers, and spent months holding up the nomination of Kevin Warsh to lead the Federal Reserve in protest of the justice department’s investigation of then chair Jerome Powell. This year, Trump has backed successful primary challenges against the Kentucky congressman Thomas Massie, who championed the release of the Epstein files; the Louisiana senator Bill Cassidy, who voted to convict Trump after the January 6 insurrection; and the Texas senator John Cornyn, who fell out of favor with the Maga movement. Cassidy, a physician, appeared to try to make amends with Trump by casting a deciding vote to confirm vaccine skeptic Robert F Kennedy Jr as the secretary of health and human services. After losing his primary, he publicly condemned Trump’s bid to create the anti-weaponization fund, then fruitlessly tried to forge a compromise to add language to the immigration enforcement spending bill the Senate passed this week to bar the payouts from ever happening. Cassidy also signed on to a court brief challenging the fund, and voted for an Iran war powers resolution. Others in the party appear to now view breaking with the president as politically expedient as they face uncertain re-election prospects in November. As the Senate was considering the immigration bill on Thursday, the Democratic minority leader, Chuck Schumer, proposed an amendment to bar the anti-weaponization fund for good. While the proposal failed, three Republican senators voted for it: Collins, the only Republican senator representing a state won by Kamala Harris in 2024; the Ohio senator Jon Husted, who a Fox News poll this week found was trailing his Democratic challenger by eight percentage points; and the Alaska senator Dan Sullivan, another target of Democrats. Even senators not facing re-election have been vexed by some of Trump’s demands. Thune and other senators have expressed skepticism at Trump’s nomination of Pulte, who now leads the Federal Housing Finance Agency, for one of the nation’s top intelligence jobs. His nomination has already complicated the GOP’s prospects of winning the necessary Democratic support for the renewal of a key surveillance law. Yet the defectors have done little to curb Trump’s powers or force him to swallow policies against his will. Despite many attempts, no war powers resolution has actually made it through Congress, and even if one did, Trump could veto it, while the effort could also face legal challenges. The “anti-weaponization” fund is dead not by law, but rather the decision of the acting attorney general, Todd Blanche, and a federal court ruling, though Trump has continued to praise it, raising fears among Democrats that he could order it reinstated. The measures providing aid to Ukraine and continuing deportation protections for Haitians have yet to pass the Senate. Doug Heye, a former House Republican leadership aide, said that the instances of Republicans standing up to the president may be less significant than they appear. The Republicans who voted for Schumer’s effort to block Trump’s payouts did so only after it became clear the amendment would fail, which Heye called a “time-honored” technique to limit an individual lawmaker’s risks on a contentious vote. “There’s nothing about it that’s unique to Trump or Mike Johnson or Thune or anything like that,” he said. And while the four Republicans who voted for the House’s Iran war powers resolution were enough to see the measure to passage, Heye argued the episode is of little significance to Trump’s overall control of the GOP. “What does it say about Trump’s hold on the party that 1.8% of the House Republican conference voted against him? I’d submit nothing,” he said.",
    "body_chars": 8249,
    "body_truncated": false,
    "url": "https://www.theguardian.com/us-news/2026/jun/06/republicans-trump-midterms",
    "section": "US news",
    "published": "2026-06-06T13:00:05Z",
    "source": "Guardian"
  }
]
