[
  {
    "question": "Will Adanech Abiebie be the next Prime Minister of Ethiopia?",
    "event_title": "Next Prime Minister of Ethiopia?",
    "event_slug": "next-prime-minister-of-ethiopia",
    "category": "",
    "is_sports": false,
    "yes_price": 0.002,
    "volume": 19040170.572521,
    "volume_24h": 3493763.766665,
    "end_date": "2026-06-01T00:00:00Z",
    "url": "https://polymarket.com/event/next-prime-minister-of-ethiopia",
    "condition_id": "0x7d0aaf81bbd3fd73b6a1651cce08a452c0cbf9c0cbb4520ce0f981065b639d88",
    "price_7d_ago": null,
    "price_change_7d": null
  },
  {
    "question": "Will Benjamin Netanyahu enter Iran by June 30?",
    "event_title": "Who will enter Iran by June 30?",
    "event_slug": "who-will-enter-iran-by-june-30",
    "category": "",
    "is_sports": false,
    "yes_price": 0.002,
    "volume": 2423867.454036,
    "volume_24h": 2368133.058333,
    "end_date": "2026-06-30T00:00:00Z",
    "url": "https://polymarket.com/event/who-will-enter-iran-by-june-30",
    "condition_id": "0x83f38b0110a93a4e68d2391dc70868ab1f8a9a074de58b0ef50d5312e3fcfcf7",
    "price_7d_ago": null,
    "price_change_7d": null
  },
  {
    "question": "Will JD Vance enter Iran by June 30?",
    "event_title": "Who will enter Iran by June 30?",
    "event_slug": "who-will-enter-iran-by-june-30",
    "category": "",
    "is_sports": false,
    "yes_price": 0.002,
    "volume": 1822296.931715,
    "volume_24h": 1783635.07,
    "end_date": "2026-06-30T00:00:00Z",
    "url": "https://polymarket.com/event/who-will-enter-iran-by-june-30",
    "condition_id": "0x77eafa497fe8ff7a41f540e2920e8897540b01f06b82477d168c4a21a7f9e57a",
    "price_7d_ago": null,
    "price_change_7d": null
  },
  {
    "question": "Strait of Hormuz traffic returns to normal by end of June?",
    "event_title": "Strait of Hormuz traffic returns to normal by end of June?",
    "event_slug": "strait-of-hormuz-traffic-returns-to-normal-by-end-of-june",
    "category": "",
    "is_sports": false,
    "yes_price": 0.05,
    "volume": 34385347.570354335,
    "volume_24h": 1543723.579189997,
    "end_date": "2026-06-30T00:00:00Z",
    "url": "https://polymarket.com/event/strait-of-hormuz-traffic-returns-to-normal-by-end-of-june",
    "condition_id": "0x348cd9adf4f6855f58bd9c6dbf9ff251c4142ef77233a5dc95c65b4b61cd2187",
    "price_7d_ago": null,
    "price_change_7d": null
  },
  {
    "question": "Will the US confirm that aliens exist by June 30?",
    "event_title": "Will the US confirm that aliens exist by...?",
    "event_slug": "will-the-us-confirm-that-aliens-exist-before-2027",
    "category": "",
    "is_sports": false,
    "yes_price": 0.006,
    "volume": 8728851.353994943,
    "volume_24h": 1160194.2621150003,
    "end_date": "2026-06-30T00:00:00Z",
    "url": "https://polymarket.com/event/will-the-us-confirm-that-aliens-exist-before-2027",
    "condition_id": "0xa7962b12241616d83dcb8c70fc33aa0f48b1ec46a3ad6a23db21d3885dedc4cb",
    "price_7d_ago": null,
    "price_change_7d": null
  },
  {
    "question": "US-Iran Final Nuclear Deal by August 31, 2026?",
    "event_title": "US-Iran Final Nuclear Deal by…?",
    "event_slug": "us-iran-final-nuclear-deal-by-20260621201254412",
    "category": "",
    "is_sports": false,
    "yes_price": 0.24,
    "volume": 1171931.9883159988,
    "volume_24h": 981215.528571,
    "end_date": "2026-08-31T23:59:00Z",
    "url": "https://polymarket.com/event/us-iran-final-nuclear-deal-by-20260621201254412",
    "condition_id": "0xa1b3158fedfddaf2a0d8b364f6a57ee68146fb6ad458222aa8e02bcf0abbb099",
    "price_7d_ago": null,
    "price_change_7d": null
  },
  {
    "question": "Will Belete Molla be the next Prime Minister of Ethiopia?",
    "event_title": "Next Prime Minister of Ethiopia?",
    "event_slug": "next-prime-minister-of-ethiopia",
    "category": "",
    "is_sports": false,
    "yes_price": 0.019,
    "volume": 11375366.256412003,
    "volume_24h": 739708.698337,
    "end_date": "2026-06-01T00:00:00Z",
    "url": "https://polymarket.com/event/next-prime-minister-of-ethiopia",
    "condition_id": "0x7c97f7315ac9a2e0eabe9b2b9caa8369feff95180483b5168a5274b69762690c",
    "price_7d_ago": null,
    "price_change_7d": null
  },
  {
    "question": "Will Hunter Biden win the 2028 Democratic presidential nomination?",
    "event_title": "Democratic Presidential Nominee 2028",
    "event_slug": "democratic-presidential-nominee-2028",
    "category": "",
    "is_sports": false,
    "yes_price": 0.008,
    "volume": 42246723.35897166,
    "volume_24h": 699978.2524450001,
    "end_date": "2028-11-07T00:00:00Z",
    "url": "https://polymarket.com/event/democratic-presidential-nominee-2028",
    "condition_id": "0x1945a8b23e313ed7423b6b6fd556f9ab5578900376b565a61dc480a5f4f35d21",
    "price_7d_ago": null,
    "price_change_7d": null
  },
  {
    "question": "Strait of Hormuz traffic returns to normal by July 15?",
    "event_title": "Strait of Hormuz traffic returns to normal by July 15?",
    "event_slug": "strait-of-hormuz-traffic-returns-to-normal-by-july-15",
    "category": "",
    "is_sports": false,
    "yes_price": 0.29,
    "volume": 3175305.162659995,
    "volume_24h": 615595.6400310001,
    "end_date": "2026-07-15T00:00:00Z",
    "url": "https://polymarket.com/event/strait-of-hormuz-traffic-returns-to-normal-by-july-15",
    "condition_id": "0xcacd424332319971356c757c025b45a4eb5643b919fb3bd2f84051afea599b13",
    "price_7d_ago": null,
    "price_change_7d": null
  },
  {
    "question": "Will Mistral have the best AI model at the end of June 2026?",
    "event_title": "Which company has best AI model end of June?",
    "event_slug": "which-company-has-best-ai-model-end-of-june",
    "category": "",
    "is_sports": false,
    "yes_price": 0.001,
    "volume": 1020223.682831006,
    "volume_24h": 600421.6833399999,
    "end_date": "2026-06-30T00:00:00Z",
    "url": "https://polymarket.com/event/which-company-has-best-ai-model-end-of-june",
    "condition_id": "0xb5bc0c62cc121183fab3645197b346b474396f52cd67622ca1010a541b955411",
    "price_7d_ago": null,
    "price_change_7d": null
  },
  {
    "question": "Will Microsoft have the best AI model at the end of June 2026?",
    "event_title": "Which company has best AI model end of June?",
    "event_slug": "which-company-has-best-ai-model-end-of-june",
    "category": "",
    "is_sports": false,
    "yes_price": 0.001,
    "volume": 672579.4995560073,
    "volume_24h": 600421.6833399999,
    "end_date": "2026-06-30T00:00:00Z",
    "url": "https://polymarket.com/event/which-company-has-best-ai-model-end-of-june",
    "condition_id": "0xce4213079b24e02ee44c724e7042ab66fc77f01fce82bfb1b20c2524250d12ef",
    "price_7d_ago": null,
    "price_change_7d": null
  },
  {
    "question": "Will Amazon have the best AI model at the end of June 2026?",
    "event_title": "Which company has best AI model end of June?",
    "event_slug": "which-company-has-best-ai-model-end-of-june",
    "category": "",
    "is_sports": false,
    "yes_price": 0.001,
    "volume": 619670.3766490084,
    "volume_24h": 600421.6833399999,
    "end_date": "2026-06-30T00:00:00Z",
    "url": "https://polymarket.com/event/which-company-has-best-ai-model-end-of-june",
    "condition_id": "0x04f08e68b89ee5f76aeec75b403bf9687ca6d2c4040e737516b9debb7cbb486b",
    "price_7d_ago": null,
    "price_change_7d": null
  },
  {
    "question": "Will ByteDance have the best AI model at the end of June 2026?",
    "event_title": "Which company has best AI model end of June?",
    "event_slug": "which-company-has-best-ai-model-end-of-june",
    "category": "",
    "is_sports": false,
    "yes_price": 0.001,
    "volume": 784178.483000008,
    "volume_24h": 600421.6833399999,
    "end_date": "2026-06-30T00:00:00Z",
    "url": "https://polymarket.com/event/which-company-has-best-ai-model-end-of-june",
    "condition_id": "0x0dc7faa4b5ee79d083532267b6bebe2e701c1801506e299193a667d710490580",
    "price_7d_ago": null,
    "price_change_7d": null
  },
  {
    "question": "Will Moonshot have the best AI model at the end of June 2026?",
    "event_title": "Which company has best AI model end of June?",
    "event_slug": "which-company-has-best-ai-model-end-of-june",
    "category": "",
    "is_sports": false,
    "yes_price": 0.001,
    "volume": 835497.2080800097,
    "volume_24h": 600421.6833399999,
    "end_date": "2026-06-30T00:00:00Z",
    "url": "https://polymarket.com/event/which-company-has-best-ai-model-end-of-june",
    "condition_id": "0x32b8fa5904645a7d096a559783121eb6c0db71487c47db0bcab99a92d5abb0dd",
    "price_7d_ago": null,
    "price_change_7d": null
  },
  {
    "question": "Will Meituan have the best AI model at the end of June 2026?",
    "event_title": "Which company has best AI model end of June?",
    "event_slug": "which-company-has-best-ai-model-end-of-june",
    "category": "",
    "is_sports": false,
    "yes_price": 0.001,
    "volume": 752992.4203610102,
    "volume_24h": 600421.6833399999,
    "end_date": "2026-06-30T00:00:00Z",
    "url": "https://polymarket.com/event/which-company-has-best-ai-model-end-of-june",
    "condition_id": "0x0a650c635145e570bfcebccf7cd63f1074d49a13d2e7a384717afeea90cf5d74",
    "price_7d_ago": null,
    "price_change_7d": null
  },
  {
    "question": "Will Baidu have the best AI model at the end of June 2026?",
    "event_title": "Which company has best AI model end of June?",
    "event_slug": "which-company-has-best-ai-model-end-of-june",
    "category": "",
    "is_sports": false,
    "yes_price": 0.001,
    "volume": 530325.5683240077,
    "volume_24h": 600421.6833399999,
    "end_date": "2026-06-30T00:00:00Z",
    "url": "https://polymarket.com/event/which-company-has-best-ai-model-end-of-june",
    "condition_id": "0x94d08baa1c18020cd133bb5eb7486001ad4336bb6a488f8ad34b679af1b58a88",
    "price_7d_ago": null,
    "price_change_7d": null
  },
  {
    "question": "Will the Iranian regime fall by June 30?",
    "event_title": "Will the Iranian regime fall by June 30?",
    "event_slug": "will-the-iranian-regime-fall-by-june-30",
    "category": "",
    "is_sports": false,
    "yes_price": 0.002,
    "volume": 64087887.921727926,
    "volume_24h": 489463.2515460017,
    "end_date": "2026-06-30T00:00:00Z",
    "url": "https://polymarket.com/event/will-the-iranian-regime-fall-by-june-30",
    "condition_id": "0x9352c559e9648ab4cab236087b64ca85c5b7123a4c7d9d7d4efde4a39c18056f",
    "price_7d_ago": null,
    "price_change_7d": null
  },
  {
    "question": "Will Alibaba have the best AI model at the end of June 2026?",
    "event_title": "Which company has best AI model end of June?",
    "event_slug": "which-company-has-best-ai-model-end-of-june",
    "category": "",
    "is_sports": false,
    "yes_price": 0.001,
    "volume": 1504005.7031520086,
    "volume_24h": 483604.95999999996,
    "end_date": "2026-06-30T00:00:00Z",
    "url": "https://polymarket.com/event/which-company-has-best-ai-model-end-of-june",
    "condition_id": "0x89102f28df8a119d84259cfdd0f2f7f9a758cfdf749554e153c6bf154afbe717",
    "price_7d_ago": null,
    "price_change_7d": null
  },
  {
    "question": "Strait of Hormuz traffic returns to normal by July 31?",
    "event_title": "Strait of Hormuz traffic returns to normal by July 31?",
    "event_slug": "strait-of-hormuz-traffic-returns-to-normal-by-july-31",
    "category": "",
    "is_sports": false,
    "yes_price": 0.47,
    "volume": 8645054.264138062,
    "volume_24h": 477402.32311400014,
    "end_date": "2026-07-31T00:00:00Z",
    "url": "https://polymarket.com/event/strait-of-hormuz-traffic-returns-to-normal-by-july-31",
    "condition_id": "0xb8e6d129a06d0ccb21d7b32eb529ea455eddba3cf29bfa097112202cbdf5bf21",
    "price_7d_ago": null,
    "price_change_7d": null
  },
  {
    "question": "Will Carlos Álvarez win the 2026 Peruvian presidential election?",
    "event_title": "Peru Presidential Election Winner",
    "event_slug": "peru-presidential-election-winner",
    "category": "",
    "is_sports": false,
    "yes_price": 0.001,
    "volume": 13204985.796722002,
    "volume_24h": 419665.148142,
    "end_date": "2026-04-12T00:00:00Z",
    "url": "https://polymarket.com/event/peru-presidential-election-winner",
    "condition_id": "0x9b14ba5cc37a35c0db2c9849e631d98195670be4a0f91233a81529f22a7a5949",
    "price_7d_ago": null,
    "price_change_7d": null
  },
  {
    "question": "Will César Acuña win the 2026 Peruvian presidential election?",
    "event_title": "Peru Presidential Election Winner",
    "event_slug": "peru-presidential-election-winner",
    "category": "",
    "is_sports": false,
    "yes_price": 0.001,
    "volume": 651993.8659779998,
    "volume_24h": 419665.148142,
    "end_date": "2026-06-07T00:00:00Z",
    "url": "https://polymarket.com/event/peru-presidential-election-winner",
    "condition_id": "0xef61cec575ac7260343e1f0c11900fee12a1f30b521b649eec7663ec5424242a",
    "price_7d_ago": null,
    "price_change_7d": null
  },
  {
    "question": "Will Vladimir Cerrón win the 2026 Peruvian presidential election?",
    "event_title": "Peru Presidential Election Winner",
    "event_slug": "peru-presidential-election-winner",
    "category": "",
    "is_sports": false,
    "yes_price": 0.001,
    "volume": 254947.48393799996,
    "volume_24h": 419665.148142,
    "end_date": "2026-06-07T00:00:00Z",
    "url": "https://polymarket.com/event/peru-presidential-election-winner",
    "condition_id": "0xa61438a389267c7deafc9d04cd6d0dc597d70253eb94702c0f5be458d75719a2",
    "price_7d_ago": null,
    "price_change_7d": null
  },
  {
    "question": "Will Roberto Chiabra win the 2026 Peruvian presidential election?",
    "event_title": "Peru Presidential Election Winner",
    "event_slug": "peru-presidential-election-winner",
    "category": "",
    "is_sports": false,
    "yes_price": 0.001,
    "volume": 140391.31482499995,
    "volume_24h": 419665.148142,
    "end_date": "2026-06-07T00:00:00Z",
    "url": "https://polymarket.com/event/peru-presidential-election-winner",
    "condition_id": "0x3aec41fee9edc59c2b98d439dba86debe339e35f62ac4cdc8de01ab1a5b93f21",
    "price_7d_ago": null,
    "price_change_7d": null
  },
  {
    "question": "Will Enrique Valderrama win the 2026 Peruvian presidential election?",
    "event_title": "Peru Presidential Election Winner",
    "event_slug": "peru-presidential-election-winner",
    "category": "",
    "is_sports": false,
    "yes_price": 0.001,
    "volume": 267190.855973,
    "volume_24h": 419665.148142,
    "end_date": "2026-06-07T00:00:00Z",
    "url": "https://polymarket.com/event/peru-presidential-election-winner",
    "condition_id": "0xd149b38c9da6bacbdc0068b579f8d255196f8c2ed6a5df67f5f3064dd00733e9",
    "price_7d_ago": null,
    "price_change_7d": null
  },
  {
    "question": "Will Mesías Guevara win the 2026 Peruvian presidential election?",
    "event_title": "Peru Presidential Election Winner",
    "event_slug": "peru-presidential-election-winner",
    "category": "",
    "is_sports": false,
    "yes_price": 0.001,
    "volume": 328092.40309500037,
    "volume_24h": 419665.148142,
    "end_date": "2026-06-07T00:00:00Z",
    "url": "https://polymarket.com/event/peru-presidential-election-winner",
    "condition_id": "0xb06bd8cd9693172502d649f157283cf4d6b15dc6d595495eed33b70e94b6565e",
    "price_7d_ago": null,
    "price_change_7d": null
  },
  {
    "question": "Will Jorge Nieto win the 2026 Peruvian presidential election?",
    "event_title": "Peru Presidential Election Winner",
    "event_slug": "peru-presidential-election-winner",
    "category": "",
    "is_sports": false,
    "yes_price": 0.001,
    "volume": 5780977.049471,
    "volume_24h": 419665.148142,
    "end_date": "2026-06-07T00:00:00Z",
    "url": "https://polymarket.com/event/peru-presidential-election-winner",
    "condition_id": "0x158fdaad572880f8de3d3f00e4d3c2fbbae77108d88c29deb800141928c1e040",
    "price_7d_ago": null,
    "price_change_7d": null
  },
  {
    "question": "Will Mario Vizcarra win the 2026 Peruvian presidential election?",
    "event_title": "Peru Presidential Election Winner",
    "event_slug": "peru-presidential-election-winner",
    "category": "",
    "is_sports": false,
    "yes_price": 0.001,
    "volume": 207788.08426700003,
    "volume_24h": 419665.148142,
    "end_date": "2026-06-07T00:00:00Z",
    "url": "https://polymarket.com/event/peru-presidential-election-winner",
    "condition_id": "0x0e7f0ffe845b05bdbd172958464fa20bcd9a048781d73e4090e07b03a4da254f",
    "price_7d_ago": null,
    "price_change_7d": null
  },
  {
    "question": "Will José Luna win the 2026 Peruvian presidential election?",
    "event_title": "Peru Presidential Election Winner",
    "event_slug": "peru-presidential-election-winner",
    "category": "",
    "is_sports": false,
    "yes_price": 0.001,
    "volume": 370858.82974200003,
    "volume_24h": 419665.148142,
    "end_date": "2026-06-07T00:00:00Z",
    "url": "https://polymarket.com/event/peru-presidential-election-winner",
    "condition_id": "0xf73e2e231d324cb662ad80eefdd90bba5007fc4df45bc2c7bab90d83693cc4ee",
    "price_7d_ago": null,
    "price_change_7d": null
  },
  {
    "question": "Will José Williams win the 2026 Peruvian presidential election?",
    "event_title": "Peru Presidential Election Winner",
    "event_slug": "peru-presidential-election-winner",
    "category": "",
    "is_sports": false,
    "yes_price": 0.001,
    "volume": 144206.89001700009,
    "volume_24h": 419665.148142,
    "end_date": "2026-06-07T00:00:00Z",
    "url": "https://polymarket.com/event/peru-presidential-election-winner",
    "condition_id": "0x7965575591c9229a2c75c881555403f5e867cd5759545619d8ec061b2b08135f",
    "price_7d_ago": null,
    "price_change_7d": null
  },
  {
    "question": "Will Fiorella Molinelli win the 2026 Peruvian presidential election?",
    "event_title": "Peru Presidential Election Winner",
    "event_slug": "peru-presidential-election-winner",
    "category": "",
    "is_sports": false,
    "yes_price": 0.001,
    "volume": 163257.98561200016,
    "volume_24h": 419665.148142,
    "end_date": "2026-06-07T00:00:00Z",
    "url": "https://polymarket.com/event/peru-presidential-election-winner",
    "condition_id": "0x5e7d3b7cf87325cee6ae6c7417d6e9d7250c4cc2dc912b18ce5cdafba4e6a647",
    "price_7d_ago": null,
    "price_change_7d": null
  },
  {
    "question": "Will Fernando Olivera win the 2026 Peruvian presidential election?",
    "event_title": "Peru Presidential Election Winner",
    "event_slug": "peru-presidential-election-winner",
    "category": "",
    "is_sports": false,
    "yes_price": 0.001,
    "volume": 472562.3604739996,
    "volume_24h": 419665.148142,
    "end_date": "2026-06-07T00:00:00Z",
    "url": "https://polymarket.com/event/peru-presidential-election-winner",
    "condition_id": "0x24a454785cac9984fde7736d0d4b37929b7253d527d359f547c909eec89862b9",
    "price_7d_ago": null,
    "price_change_7d": null
  },
  {
    "question": "Will Yonhy Lescano win the 2026 Peruvian presidential election?",
    "event_title": "Peru Presidential Election Winner",
    "event_slug": "peru-presidential-election-winner",
    "category": "",
    "is_sports": false,
    "yes_price": 0.001,
    "volume": 440432.1633020003,
    "volume_24h": 419665.148142,
    "end_date": "2026-06-07T00:00:00Z",
    "url": "https://polymarket.com/event/peru-presidential-election-winner",
    "condition_id": "0x6a58844c4dfdf677adb5e20bcefb851833cb335210e139ce37e63482e0679617",
    "price_7d_ago": null,
    "price_change_7d": null
  },
  {
    "question": "Will Alfonso López Chau win the 2026 Peruvian presidential election?",
    "event_title": "Peru Presidential Election Winner",
    "event_slug": "peru-presidential-election-winner",
    "category": "",
    "is_sports": false,
    "yes_price": 0.001,
    "volume": 2319043.686239003,
    "volume_24h": 419665.148142,
    "end_date": "2026-06-07T00:00:00Z",
    "url": "https://polymarket.com/event/peru-presidential-election-winner",
    "condition_id": "0x78f5630bafa15147941daa2fd2926b43febe6af1544cd9d8527b226914f3ca11",
    "price_7d_ago": null,
    "price_change_7d": null
  },
  {
    "question": "Will George Forsyth win the 2026 Peruvian presidential election?",
    "event_title": "Peru Presidential Election Winner",
    "event_slug": "peru-presidential-election-winner",
    "category": "",
    "is_sports": false,
    "yes_price": 0.001,
    "volume": 282707.6370279996,
    "volume_24h": 419665.148142,
    "end_date": "2026-06-07T00:00:00Z",
    "url": "https://polymarket.com/event/peru-presidential-election-winner",
    "condition_id": "0x82d5ffbcda5dc4cb5039bd59224c732c465dc6c052af3257f38055e8dc66b0bf",
    "price_7d_ago": null,
    "price_change_7d": null
  },
  {
    "question": "Will Ricardo Belmont win the 2026 Peruvian presidential election?",
    "event_title": "Peru Presidential Election Winner",
    "event_slug": "peru-presidential-election-winner",
    "category": "",
    "is_sports": false,
    "yes_price": 0.001,
    "volume": 4348908.602431993,
    "volume_24h": 419665.148142,
    "end_date": "2026-06-07T00:00:00Z",
    "url": "https://polymarket.com/event/peru-presidential-election-winner",
    "condition_id": "0x0a10ea4f5d42ac33a29d73b8562f4414f5ea2219afd9da74ba950f7aefe7c630",
    "price_7d_ago": null,
    "price_change_7d": null
  },
  {
    "question": "Will Carlos Espá win the 2026 Peruvian presidential election?",
    "event_title": "Peru Presidential Election Winner",
    "event_slug": "peru-presidential-election-winner",
    "category": "",
    "is_sports": false,
    "yes_price": 0.001,
    "volume": 1816789.446928001,
    "volume_24h": 419665.148142,
    "end_date": "2026-06-07T00:00:00Z",
    "url": "https://polymarket.com/event/peru-presidential-election-winner",
    "condition_id": "0x974dcbcce5e8186e0e273065a60675bc17617897c395eca60478d0c49f80718f",
    "price_7d_ago": null,
    "price_change_7d": null
  },
  {
    "question": "Will Rafael Belaúnde Llosa win the 2026 Peruvian presidential election?",
    "event_title": "Peru Presidential Election Winner",
    "event_slug": "peru-presidential-election-winner",
    "category": "",
    "is_sports": false,
    "yes_price": 0.001,
    "volume": 224872.05037800013,
    "volume_24h": 419665.148142,
    "end_date": "2026-06-07T00:00:00Z",
    "url": "https://polymarket.com/event/peru-presidential-election-winner",
    "condition_id": "0x790d04324ceda5e7fd3b2e62cf043d45b74a9d88921b6b250212d0c9b8ba1afd",
    "price_7d_ago": null,
    "price_change_7d": null
  },
  {
    "question": "Will Marisol Pérez Tello win the 2026 Peruvian presidential election?",
    "event_title": "Peru Presidential Election Winner",
    "event_slug": "peru-presidential-election-winner",
    "category": "",
    "is_sports": false,
    "yes_price": 0.001,
    "volume": 1743418.2730179995,
    "volume_24h": 419665.148142,
    "end_date": "2026-06-07T00:00:00Z",
    "url": "https://polymarket.com/event/peru-presidential-election-winner",
    "condition_id": "0x28d4cee5a4bb01e0a7b1a39f8a23b2af657d9cf06d1e0ed8443c6b09329b9be3",
    "price_7d_ago": null,
    "price_change_7d": null
  },
  {
    "question": "Will Wolfgang Grozo win the 2026 Peruvian presidential election?",
    "event_title": "Peru Presidential Election Winner",
    "event_slug": "peru-presidential-election-winner",
    "category": "",
    "is_sports": false,
    "yes_price": 0.001,
    "volume": 736593.6290500003,
    "volume_24h": 419665.148142,
    "end_date": "2026-06-07T00:00:00Z",
    "url": "https://polymarket.com/event/peru-presidential-election-winner",
    "condition_id": "0xe18a1286c10eb4e5d6b67a81e0164425366e5dc08f9cf36e979c48d24eca569d",
    "price_7d_ago": null,
    "price_change_7d": null
  },
  {
    "question": "Will Tulsi Gabbard win the 2028 US Presidential Election?",
    "event_title": "Presidential Election Winner 2028",
    "event_slug": "presidential-election-winner-2028",
    "category": "",
    "is_sports": false,
    "yes_price": 0.008,
    "volume": 32787676.059570853,
    "volume_24h": 382902.95155700005,
    "end_date": "2028-11-07T00:00:00Z",
    "url": "https://polymarket.com/event/presidential-election-winner-2028",
    "condition_id": "0x8fc141205ebce5adf437bfdf4d0c5ff58ff24293b79c9431991346c208bb48ed",
    "price_7d_ago": null,
    "price_change_7d": null
  },
  {
    "question": "Will Uzbekistan win the 2026 FIFA World Cup?",
    "event_title": "World Cup Winner",
    "event_slug": "world-cup-winner",
    "category": "",
    "is_sports": true,
    "yes_price": 0.001,
    "volume": 61465432.538417585,
    "volume_24h": 57286957.75711298,
    "end_date": "2026-07-20T00:00:00Z",
    "url": "https://polymarket.com/event/world-cup-winner",
    "condition_id": "0x965ebc5d79eb1ec02cad67245a44b9e45b33359018f013fb6cf81d5bbf7bcc8d",
    "price_7d_ago": null,
    "price_change_7d": null
  },
  {
    "question": "Spread: Haiti (-5.5)",
    "event_title": "Morocco vs. Haiti - More Markets",
    "event_slug": "fifwc-mar-hai-2026-06-24-more-markets",
    "category": "",
    "is_sports": true,
    "yes_price": 0.0005,
    "volume": 578.101,
    "volume_24h": 28101375.197199017,
    "end_date": "2026-06-24T22:00:00Z",
    "url": "https://polymarket.com/event/fifwc-mar-hai-2026-06-24-more-markets",
    "condition_id": "0x36f648ef5117997bfccbc40c1e7940f98f21898c69175fdb1d5f1d65ec6a0dc6",
    "price_7d_ago": null,
    "price_change_7d": null
  },
  {
    "question": "Spread: Haiti (-3.5)",
    "event_title": "Morocco vs. Haiti - More Markets",
    "event_slug": "fifwc-mar-hai-2026-06-24-more-markets",
    "category": "",
    "is_sports": true,
    "yes_price": 0.0005,
    "volume": 679.8563999999997,
    "volume_24h": 28101375.197199017,
    "end_date": "2026-06-24T22:00:00Z",
    "url": "https://polymarket.com/event/fifwc-mar-hai-2026-06-24-more-markets",
    "condition_id": "0xf38e4b8c04b6f013e1c3fb25ec08bd20de654577ea1f869add7dd3dfb4a4d5f7",
    "price_7d_ago": null,
    "price_change_7d": null
  },
  {
    "question": "Spread: Haiti (-4.5)",
    "event_title": "Morocco vs. Haiti - More Markets",
    "event_slug": "fifwc-mar-hai-2026-06-24-more-markets",
    "category": "",
    "is_sports": true,
    "yes_price": 0.01,
    "volume": 660.0799999999999,
    "volume_24h": 28101375.197199017,
    "end_date": "2026-06-24T22:00:00Z",
    "url": "https://polymarket.com/event/fifwc-mar-hai-2026-06-24-more-markets",
    "condition_id": "0x7e2bfe6032fd8c1151e68809d0ebf688bef3f956e1ebdbbfd35dfea7069c4db5",
    "price_7d_ago": null,
    "price_change_7d": null
  },
  {
    "question": "Spread: Morocco (-1.5)",
    "event_title": "Morocco vs. Haiti - More Markets",
    "event_slug": "fifwc-mar-hai-2026-06-24-more-markets",
    "category": "",
    "is_sports": true,
    "yes_price": 0.33,
    "volume": 16245003.133957988,
    "volume_24h": 16208692.439145016,
    "end_date": "2026-06-24T22:00:00Z",
    "url": "https://polymarket.com/event/fifwc-mar-hai-2026-06-24-more-markets",
    "condition_id": "0xf0164e968314bae58a0440248e2abd20ee9e4704df2b24c98c50072006b26315",
    "price_7d_ago": null,
    "price_change_7d": null
  },
  {
    "question": "Will Morocco win on 2026-06-24?",
    "event_title": "Morocco vs. Haiti",
    "event_slug": "fifwc-mar-hai-2026-06-24",
    "category": "",
    "is_sports": true,
    "yes_price": 0.63,
    "volume": 11532029.61155719,
    "volume_24h": 11367615.50528006,
    "end_date": "2026-06-24T22:00:00Z",
    "url": "https://polymarket.com/event/fifwc-mar-hai-2026-06-24",
    "condition_id": "0x649bd3dc845f647aa8c9a739ad8de245b853224961afd01127de0071c13f84b3",
    "price_7d_ago": null,
    "price_change_7d": null
  },
  {
    "question": "Scotland vs. Brazil: Scotland 2nd Half O/U 1.5",
    "event_title": "Scotland vs. Brazil - More Markets",
    "event_slug": "fifwc-sco-bra-2026-06-24-more-markets",
    "category": "",
    "is_sports": true,
    "yes_price": 0.455,
    "volume": null,
    "volume_24h": 10182375.847857997,
    "end_date": "2026-06-24T22:00:00Z",
    "url": "https://polymarket.com/event/fifwc-sco-bra-2026-06-24-more-markets",
    "condition_id": "0x0fe6c0f30013fb64ab86781b0f43bbc85f87106cb7dea9d21b65828627e0d438",
    "price_7d_ago": null,
    "price_change_7d": null
  },
  {
    "question": "Spread: Scotland (-5.5)",
    "event_title": "Scotland vs. Brazil - More Markets",
    "event_slug": "fifwc-sco-bra-2026-06-24-more-markets",
    "category": "",
    "is_sports": true,
    "yes_price": 0.0005,
    "volume": 1050.526,
    "volume_24h": 10182375.847857997,
    "end_date": "2026-06-24T22:00:00Z",
    "url": "https://polymarket.com/event/fifwc-sco-bra-2026-06-24-more-markets",
    "condition_id": "0x8e3ee41e9a516d768171c1d0bb3557015fe44b6b420d7c1a3da2f9fb765fbefb",
    "price_7d_ago": null,
    "price_change_7d": null
  },
  {
    "question": "Will Bosnia-Herzegovina win the 2026 FIFA World Cup?",
    "event_title": "World Cup Winner",
    "event_slug": "world-cup-winner",
    "category": "",
    "is_sports": true,
    "yes_price": 0.001,
    "volume": 55383365.50971779,
    "volume_24h": 8333209.024,
    "end_date": "2026-07-20T00:00:00Z",
    "url": "https://polymarket.com/event/world-cup-winner",
    "condition_id": "0xbce6698c9a61376c0709a2a724a9cf0dd0236d8dea882533073b6bb062efbee0",
    "price_7d_ago": null,
    "price_change_7d": null
  },
  {
    "question": "Will Brazil win on 2026-06-24?",
    "event_title": "Scotland vs. Brazil",
    "event_slug": "fifwc-sco-bra-2026-06-24",
    "category": "",
    "is_sports": true,
    "yes_price": 0.972,
    "volume": 6475338.217466943,
    "volume_24h": 6182946.549335954,
    "end_date": "2026-06-24T22:00:00Z",
    "url": "https://polymarket.com/event/fifwc-sco-bra-2026-06-24",
    "condition_id": "0xd14544ac7360f37de17eb6a442694de21a8c5ea01714323be6409b002c4d7d7d",
    "price_7d_ago": null,
    "price_change_7d": null
  }
]
